Workbook

Sheet Painel
B2: PAINEL DE COMPRAS
B3: Visão consolidada dos gastos — tudo em fórmula: atualiza sozinho ao adicionar compras na aba Compras
B5: TOTAL GASTO | C5: ITENS | D5: TICKET MÉDIO | E5: MERCADOS | F5: PERÍODO
B6: =SUM(tblCompras[Total Pago]) -> 5963.22 | C6: =COUNTA(tblCompras[Produto]) -> 671 | D6: =IFERROR(B6/C6,0) -> 8.8870641 | E6: =SUMPRODUCT(1/COUNTIF(tblCompras[Mercado],tblCompras[Mercado])) -> 13 | F6: =DAY(MIN(tblCompras[Data]))&"/"&MONTH(MIN(tblCompras[Data]))&" → "&DAY(MAX(tblCompras[Data]))&"/"&MONTH(MAX(tblCompras[Data]))&"/"&YEAR(MAX(tblCompras[Data])) -> 2/5 → 10/8/2026
B9: ONDE VOCÊ ESTÁ GASTANDO
B10: Total por categoria (todas as categorias encontradas na aba Compras)
B12: Categoria | C12: Total | D12: %
B13: Mercearia | C13: =SUMIF(tblCompras[Categoria],B13,tblCompras[Total Pago]) -> 2590.26 | D13: =IFERROR(C13/$B$6,0) -> 0.4343727
B14: Laticinios | C14: =SUMIF(tblCompras[Categoria],B14,tblCompras[Total Pago]) -> 871.89 | D14: =IFERROR(C14/$B$6,0) -> 0.14621128
B15: Padaria | C15: =SUMIF(tblCompras[Categoria],B15,tblCompras[Total Pago]) -> 845.46 | D15: =IFERROR(C15/$B$6,0) -> 0.14177911
B16: Hortifruti | C16: =SUMIF(tblCompras[Categoria],B16,tblCompras[Total Pago]) -> 547.56 | D16: =IFERROR(C16/$B$6,0) -> 0.091822874
B17: Bebidas | C17: =SUMIF(tblCompras[Categoria],B17,tblCompras[Total Pago]) -> 311.84 | D17: =IFERROR(C17/$B$6,0) -> 0.052293895
B18: Carnes | C18: =SUMIF(tblCompras[Categoria],B18,tblCompras[Total Pago]) -> 205.97 | D18: =IFERROR(C18/$B$6,0) -> 0.034540064
B19: Higiene | C19: =SUMIF(tblCompras[Categoria],B19,tblCompras[Total Pago]) -> 164.96 | D19: =IFERROR(C19/$B$6,0) -> 0.027662907
B20: Limpeza | C20: =SUMIF(tblCompras[Categoria],B20,tblCompras[Total Pago]) -> 141.39 | D20: =IFERROR(C20/$B$6,0) -> 0.023710344
B21: Laticínios | C21: =SUMIF(tblCompras[Categoria],B21,tblCompras[Total Pago]) -> 73.92 | D21: =IFERROR(C21/$B$6,0) -> 0.012395987
B22: Saúde | C22: =SUMIF(tblCompras[Categoria],B22,tblCompras[Total Pago]) -> 51.15 | D22: =IFERROR(C22/$B$6,0) -> 0.0085775806
B23: Pet | C23: =SUMIF(tblCompras[Categoria],B23,tblCompras[Total Pago]) -> 43.81 | D23: =IFERROR(C23/$B$6,0) -> 0.0073467019
B24: Café | C24: =SUMIF(tblCompras[Categoria],B24,tblCompras[Total Pago]) -> 34.6 | D24: =IFERROR(C24/$B$6,0) -> 0.0058022344
... B28: Frutas | C28: =SUMIF(tblCompras[Categoria],B28,tblCompras[Total Pago]) -> 5.04 | D28: =IFERROR(C28/$B$6,0) -> 0.00084518096
B29: Total | C29: =SUM(C13:C28) -> 5963.22 | D29: =SUM(D13:D28) -> 1
B32: EVOLUÇÃO POR MÊS
B33: Quanto você gastou em cada mês (meses gerados automaticamente)
B35: Mês/Ano | C35: Total | D35: Itens
B36: =IF(Listas!E6="","",Listas!E6) -> mai/2026 | C36: =IF($B36="","",SUMIFS(tblCompras[Total Pago],tblCompras[Data],">="&Listas!$H$6,tblCompras[Data],"<="&EOMONTH(Listas!$H$6,0))) -> 2153.03 | D36: =IF($B36="","",COUNTIFS(tblCompras[Data],">="&Listas!$H$6,tblCompras[Data],"<="&EOMONTH(Listas!$H$6,0))) -> 240
B37: =IF(Listas!E7="","",Listas!E7) -> jun/2026 | C37: =IF($B37="","",SUMIFS(tblCompras[Total Pago],tblCompras[Data],">="&Listas!$H$7,tblCompras[Data],"<="&EOMONTH(Listas!$H$7,0))) -> 1585.03 | D37: =IF($B37="","",COUNTIFS(tblCompras[Data],">="&Listas!$H$7,tblCompras[Data],"<="&EOMONTH(Listas!$H$7,0))) -> 199
B38: =IF(Listas!E8="","",Listas!E8) -> jul/2026 | C38: =IF($B38="","",SUMIFS(tblCompras[Total Pago],tblCompras[Data],">="&Listas!$H$8,tblCompras[Data],"<="&EOMONTH(Listas!$H$8,0))) -> 1969.23 | D38: =IF($B38="","",COUNTIFS(tblCompras[Data],">="&Listas!$H$8,tblCompras[Data],"<="&EOMONTH(Listas!$H$8,0))) -> 207
B39: =IF(Listas!E9="","",Listas!E9) -> ago/2026 | C39: =IF($B39="","",SUMIFS(tblCompras[Total Pago],tblCompras[Data],">="&Listas!$H$9,tblCompras[Data],"<="&EOMONTH(Listas!$H$9,0))) -> 255.93 | D39: =IF($B39="","",COUNTIFS(tblCompras[Data],">="&Listas!$H$9,tblCompras[Data],"<="&EOMONTH(Listas!$H$9,0))) -> 25
B40: =IF(Listas!E10="","",Listas!E10) | C40: =IF($B40="","",SUMIFS(tblCompras[Total Pago],tblCompras[Data],">="&Listas!$H$10,tblCompras[Data],"<="&EOMONTH(Listas!$H$10,0))) | D40: =IF($B40="","",COUNTIFS(tblCompras[Data],">="&Listas!$H$10,tblCompras[Data],"<="&EOMONTH(Listas!$H$10,0)))
B41: =IF(Listas!E11="","",Listas!E11) | C41: =IF($B41="","",SUMIFS(tblCompras[Total Pago],tblCompras[Data],">="&Listas!$H$11,tblCompras[Data],"<="&EOMONTH(Listas!$H$11,0))) | D41: =IF($B41="","",COUNTIFS(tblCompras[Data],">="&Listas!$H$11,tblCompras[Data],"<="&EOMONTH(Listas!$H$11,0)))
B42: =IF(Listas!E12="","",Listas!E12) | C42: =IF($B42="","",SUMIFS(tblCompras[Total Pago],tblCompras[Data],">="&Listas!$H$12,tblCompras[Data],"<="&EOMONTH(Listas!$H$12,0))) | D42: =IF($B42="","",COUNTIFS(tblCompras[Data],">="&Listas!$H$12,tblCompras[Data],"<="&EOMONTH(Listas!$H$12,0)))
B43: =IF(Listas!E13="","",Listas!E13) | C43: =IF($B43="","",SUMIFS(tblCompras[Total Pago],tblCompras[Data],">="&Listas!$H$13,tblCompras[Data],"<="&EOMONTH(Listas!$H$13,0))) | D43: =IF($B43="","",COUNTIFS(tblCompras[Data],">="&Listas!$H$13,tblCompras[Data],"<="&EOMONTH(Listas!$H$13,0)))
B44: =IF(Listas!E14="","",Listas!E14) | C44: =IF($B44="","",SUMIFS(tblCompras[Total Pago],tblCompras[Data],">="&Listas!$H$14,tblCompras[Data],"<="&EOMONTH(Listas!$H$14,0))) | D44: =IF($B44="","",COUNTIFS(tblCompras[Data],">="&Listas!$H$14,tblCompras[Data],"<="&EOMONTH(Listas!$H$14,0)))
B45: =IF(Listas!E15="","",Listas!E15) | C45: =IF($B45="","",SUMIFS(tblCompras[Total Pago],tblCompras[Data],">="&Listas!$H$15,tblCompras[Data],"<="&EOMONTH(Listas!$H$15,0))) | D45: =IF($B45="","",COUNTIFS(tblCompras[Data],">="&Listas!$H$15,tblCompras[Data],"<="&EOMONTH(Listas!$H$15,0)))
B46: =IF(Listas!E16="","",Listas!E16) | C46: =IF($B46="","",SUMIFS(tblCompras[Total Pago],tblCompras[Data],">="&Listas!$H$16,tblCompras[Data],"<="&EOMONTH(Listas!$H$16,0))) | D46: =IF($B46="","",COUNTIFS(tblCompras[Data],">="&Listas!$H$16,tblCompras[Data],"<="&EOMONTH(Listas!$H$16,0)))
B47: =IF(Listas!E17="","",Listas!E17) | C47: =IF($B47="","",SUMIFS(tblCompras[Total Pago],tblCompras[Data],">="&Listas!$H$17,tblCompras[Data],"<="&EOMONTH(Listas!$H$17,0))) | D47: =IF($B47="","",COUNTIFS(tblCompras[Data],">="&Listas!$H$17,tblCompras[Data],"<="&EOMONTH(Listas!$H$17,0)))
B48: Total | C48: =SUM(C36:C47) -> 5963.22 | D48: =SUM(D36:D47) -> 671
B51: POR MERCADO
B52: Quanto você gastou em cada lugar
B54: Mercado | C54: Total | D54: Itens | E54: Ticket | F54: %
B55: Supermercados Nori | C55: =SUMIF(tblCompras[Mercado],$B55,tblCompras[Total Pago]) -> 3935.17 | D55: =COUNTIF(tblCompras[Mercado],$B55) -> 437 | E55: =IFERROR(C55/D55,0) -> 9.0049657 | F55: =IFERROR(C55/$B$6,0) -> 0.6599069
B56: Supermercado Canesin | C56: =SUMIF(tblCompras[Mercado],$B56,tblCompras[Total Pago]) -> 959.88 | D56: =COUNTIF(tblCompras[Mercado],$B56) -> 112 | E56: =IFERROR(C56/D56,0) -> 8.5703571 | F56: =IFERROR(C56/$B$6,0) -> 0.16096673
B57: Varejao Monteverde | C57: =SUMIF(tblCompras[Mercado],$B57,tblCompras[Total Pago]) -> 547.35 | D57: =COUNTIF(tblCompras[Mercado],$B57) -> 77 | E57: =IFERROR(C57/D57,0) -> 7.1084416 | F57: =IFERROR(C57/$B$6,0) -> 0.091787658
B58: Andre Eduardo Hipolito | C58: =SUMIF(tblCompras[Mercado],$B58,tblCompras[Total Pago]) -> 148.6 | D58: =COUNTIF(tblCompras[Mercado],$B58) -> 18 | E58: =IFERROR(C58/D58,0) -> 8.2555556 | F58: =IFERROR(C58/$B$6,0) -> 0.024919423
B59: Varejao Nova Brasil | C59: =SUMIF(tblCompras[Mercado],$B59,tblCompras[Total Pago]) -> 81.9 | D59: =COUNTIF(tblCompras[Mercado],$B59) -> 7 | E59: =IFERROR(C59/D59,0) -> 11.7 | F59: =IFERROR(C59/$B$6,0) -> 0.013734191
B60: Casa de Carnes Barao da Carne | C60: =SUMIF(tblCompras[Mercado],$B60,tblCompras[Total Pago]) -> 78.48 | D60: =COUNTIF(tblCompras[Mercado],$B60) -> 2 | E60: =IFERROR(C60/D60,0) -> 39.24 | F60: =IFERROR(C60/$B$6,0) -> 0.013160675
B61: Lanchoti e Martins | C61: =SUMIF(tblCompras[Mercado],$B61,tblCompras[Total Pago]) -> 51.15 | D61: =COUNTIF(tblCompras[Mercado],$B61) -> 2 | E61: =IFERROR(C61/D61,0) -> 25.575 | F61: =IFERROR(C61/$B$6,0) -> 0.0085775806
B62: Andre Novato Ribeiro | C62: =SUMIF(tblCompras[Mercado],$B62,tblCompras[Total Pago]) -> 39.98 | D62: =COUNTIF(tblCompras[Mercado],$B62) -> 2 | E62: =IFERROR(C62/D62,0) -> 19.99 | F62: =IFERROR(C62/$B$6,0) -> 0.0067044315
B63: Real Atacamix | C63: =SUMIF(tblCompras[Mercado],$B63,tblCompras[Total Pago]) -> 39.96 | D63: =COUNTIF(tblCompras[Mercado],$B63) -> 3 | E63: =IFERROR(C63/D63,0) -> 13.32 | F63: =IFERROR(C63/$B$6,0) -> 0.0067010776
B64: Crystal | C64: =SUMIF(tblCompras[Mercado],$B64,tblCompras[Total Pago]) -> 27.67 | D64: =COUNTIF(tblCompras[Mercado],$B64) -> 3 | E64: =IFERROR(C64/D64,0) -> 9.2233333 | F64: =IFERROR(C64/$B$6,0) -> 0.0046401105
B65: André | C65: =SUMIF(tblCompras[Mercado],$B65,tblCompras[Total Pago]) -> 20.92 | D65: =COUNTIF(tblCompras[Mercado],$B65) -> 3 | E65: =IFERROR(C65/D65,0) -> 6.9733333 | F65: =IFERROR(C65/$B$6,0) -> 0.0035081718
B66: Andre Supermercado | C66: =SUMIF(tblCompras[Mercado],$B66,tblCompras[Total Pago]) -> 18.18 | D66: =COUNTIF(tblCompras[Mercado],$B66) -> 3 | E66: =IFERROR(C66/D66,0) -> 6.06 | F66: =IFERROR(C66/$B$6,0) -> 0.0030486885
B67: Canesin | C67: =SUMIF(tblCompras[Mercado],$B67,tblCompras[Total Pago]) -> 13.98 | D67: =COUNTIF(tblCompras[Mercado],$B67) -> 2 | E67: =IFERROR(C67/D67,0) -> 6.99 | F67: =IFERROR(C67/$B$6,0) -> 0.002344371
B68: Total | C68: =SUM(C55:C67) -> 5963.22 | D68: =SUM(D55:D67) -> 671 | E68: =IFERROR(C68/D68,0) -> 8.8870641 | F68: =SUM(F55:F67) -> 1
B71: TOP 10 ITENS MAIS CAROS
B72: Maiores valores pagos em um único item (empates repetem o primeiro produto encontrado)
B74: # | C74: Produto | D74: Mercado | E74: Valor
B75: 1 | C75: =IFERROR(INDEX(tblCompras[Produto],MATCH($E75,tblCompras[Total Pago],0)),"") -> QUEIJO MUSSARELA MANDAKA | D75: =IFERROR(INDEX(tblCompras[Mercado],MATCH($E75,tblCompras[Total Pago],0)),"") -> Supermercados Nori | E75: =IFERROR(LARGE(tblCompras[Total Pago],1),0) -> 56.1
B76: 2 | C76: =IFERROR(INDEX(tblCompras[Produto],MATCH($E76,tblCompras[Total Pago],0)),"") -> BOLO ANIVERSARIO | D76: =IFERROR(INDEX(tblCompras[Mercado],MATCH($E76,tblCompras[Total Pago],0)),"") -> Supermercados Nori | E76: =IFERROR(LARGE(tblCompras[Total Pago],2),0) -> 55.77
B77: 3 | C77: =IFERROR(INDEX(tblCompras[Produto],MATCH($E77,tblCompras[Total Pago],0)),"") -> PERNIL CARNEIRO TEMP | D77: =IFERROR(INDEX(tblCompras[Mercado],MATCH($E77,tblCompras[Total Pago],0)),"") -> Casa de Carnes Barao da Carne | E77: =IFERROR(LARGE(tblCompras[Total Pago],3),0) -> 44.26
B78: 4 | C78: =IFERROR(INDEX(tblCompras[Produto],MATCH($E78,tblCompras[Total Pago],0)),"") -> VALDA DIET 50GR | D78: =IFERROR(INDEX(tblCompras[Mercado],MATCH($E78,tblCompras[Total Pago],0)),"") -> Lanchoti e Martins | E78: =IFERROR(LARGE(tblCompras[Total Pago],4),0) -> 34.56
B79: 5 | C79: =IFERROR(INDEX(tblCompras[Produto],MATCH($E79,tblCompras[Total Pago],0)),"") -> COSTELINHA TEMP SUIN | D79: =IFERROR(INDEX(tblCompras[Mercado],MATCH($E79,tblCompras[Total Pago],0)),"") -> Casa de Carnes Barao da Carne | E79: =IFERROR(LARGE(tblCompras[Total Pago],5),0) -> 34.22
B80: 6 | C80: =IFERROR(INDEX(tblCompras[Produto],MATCH($E80,tblCompras[Total Pago],0)),"") -> CAFE TM 3 CORACOES | D80: =IFERROR(INDEX(tblCompras[Mercado],MATCH($E80,tblCompras[Total Pago],0)),"") -> Supermercados Nori | E80: =IFERROR(LARGE(tblCompras[Total Pago],6),0) -> 31.7
B81: 7 | C81: =IFERROR(INDEX(tblCompras[Produto],MATCH($E81,tblCompras[Total Pago],0)),"") -> CAFE TM UTAM | D81: =IFERROR(INDEX(tblCompras[Mercado],MATCH($E81,tblCompras[Total Pago],0)),"") -> Supermercados Nori | E81: =IFERROR(LARGE(tblCompras[Total Pago],7),0) -> 30.99
B82: 8 | C82: =IFERROR(INDEX(tblCompras[Produto],MATCH($E82,tblCompras[Total Pago],0)),"") -> Café Padrão 500g | D82: =IFERROR(INDEX(tblCompras[Mercado],MATCH($E82,tblCompras[Total Pago],0)),"") -> Andre Novato Ribeiro | E82: =IFERROR(LARGE(tblCompras[Total Pago],8),0) -> 29.99
B83: 9 | C83: =IFERROR(INDEX(tblCompras[Produto],MATCH($E83,tblCompras[Total Pago],0)),"") -> Café Padrão 500g | D83: =IFERROR(INDEX(tblCompras[Mercado],MATCH($E83,tblCompras[Total Pago],0)),"") -> Andre Novato Ribeiro | E83: =IFERROR(LARGE(tblCompras[Total Pago],9),0) -> 29.99
B84: 10 | C84: =IFERROR(INDEX(tblCompras[Produto],MATCH($E84,tblCompras[Total Pago],0)),"") -> MAIONESE DE LEGUMES | D84: =IFERROR(INDEX(tblCompras[Mercado],MATCH($E84,tblCompras[Total Pago],0)),"") -> Supermercados Nori | E84: =IFERROR(LARGE(tblCompras[Total Pago],10),0) -> 29.44

Sheet Análise Dinâmica
B2: ANÁLISE DINÂMICA
B3: Escolha os filtros abaixo (células amarelas) — todos os números e gráficos recalculam na hora
M4: aux
B5: MÊS/ANO | D5: CATEGORIA | F5: MERCADO | M5: =IFERROR(MATCH($B$6,Listas!$E$6:$E$17,0),0) -> 3
B6: jul/2026 | D6: (Todos) | F6: (Todos) | M6: =IF($M$5=0,DATE(1900,1,1),EOMONTH(MIN(tblCompras[Data]),$M$5-2)+1) -> 46204
M7: =IF($M$5=0,DATE(9999,12,31),EOMONTH($M$6,0)) -> 46234
B8: TOTAL (filtro) | C8: ITENS (filtro) | D8: TICKET MÉDIO | E8: % DO TOTAL GERAL
B9: =SUMIFS(tblCompras[Total Pago],tblCompras[Data],">="&$M$6,tblCompras[Data],"<="&$M$7,tblCompras[Categoria],IF($D$6="(Todos)","*",$D$6),tblCompras[Mercado],IF($F$6="(Todos)","*",$F$6)) -> 1969.23 | C9: =COUNTIFS(tblCompras[Data],">="&$M$6,tblCompras[Data],"<="&$M$7,tblCompras[Categoria],IF($D$6="(Todos)","*",$D$6),tblCompras[Mercado],IF($F$6="(Todos)","*",$F$6)) -> 207 | D9: =IFERROR(B9/C9,0) -> 9.5131884 | E9: =IFERROR(B9/SUM(tblCompras[Total Pago]),0) -> 0.33022931
B12: GASTO POR CATEGORIA
B13: Aplica os filtros de mês e mercado
B15: Categoria | C15: Total
B16: Mercearia | C16: =SUMIFS(tblCompras[Total Pago],tblCompras[Categoria],$B16,tblCompras[Data],">="&$M$6,tblCompras[Data],"<="&$M$7,tblCompras[Mercado],IF($F$6="(Todos)","*",$F$6)) -> 862.17
B17: Laticinios | C17: =SUMIFS(tblCompras[Total Pago],tblCompras[Categoria],$B17,tblCompras[Data],">="&$M$6,tblCompras[Data],"<="&$M$7,tblCompras[Mercado],IF($F$6="(Todos)","*",$F$6)) -> 338.09
B18: Padaria | C18: =SUMIFS(tblCompras[Total Pago],tblCompras[Categoria],$B18,tblCompras[Data],">="&$M$6,tblCompras[Data],"<="&$M$7,tblCompras[Mercado],IF($F$6="(Todos)","*",$F$6)) -> 332.25
B19: Hortifruti | C19: =SUMIFS(tblCompras[Total Pago],tblCompras[Categoria],$B19,tblCompras[Data],">="&$M$6,tblCompras[Data],"<="&$M$7,tblCompras[Mercado],IF($F$6="(Todos)","*",$F$6)) -> 169.31
B20: Bebidas | C20: =SUMIFS(tblCompras[Total Pago],tblCompras[Categoria],$B20,tblCompras[Data],">="&$M$6,tblCompras[Data],"<="&$M$7,tblCompras[Mercado],IF($F$6="(Todos)","*",$F$6)) -> 122.28
B21: Carnes | C21: =SUMIFS(tblCompras[Total Pago],tblCompras[Categoria],$B21,tblCompras[Data],">="&$M$6,tblCompras[Data],"<="&$M$7,tblCompras[Mercado],IF($F$6="(Todos)","*",$F$6)) -> 69.08
B22: Higiene | C22: =SUMIFS(tblCompras[Total Pago],tblCompras[Categoria],$B22,tblCompras[Data],">="&$M$6,tblCompras[Data],"<="&$M$7,tblCompras[Mercado],IF($F$6="(Todos)","*",$F$6)) -> 38.82
B23: Limpeza | C23: =SUMIFS(tblCompras[Total Pago],tblCompras[Categoria],$B23,tblCompras[Data],">="&$M$6,tblCompras[Data],"<="&$M$7,tblCompras[Mercado],IF($F$6="(Todos)","*",$F$6)) -> 37.23
B24: Laticínios | C24: =SUMIFS(tblCompras[Total Pago],tblCompras[Categoria],$B24,tblCompras[Data],">="&$M$6,tblCompras[Data],"<="&$M$7,tblCompras[Mercado],IF($F$6="(Todos)","*",$F$6)) -> 0
B25: Saúde | C25: =SUMIFS(tblCompras[Total Pago],tblCompras[Categoria],$B25,tblCompras[Data],">="&$M$6,tblCompras[Data],"<="&$M$7,tblCompras[Mercado],IF($F$6="(Todos)","*",$F$6)) -> 0
B26: Pet | C26: =SUMIFS(tblCompras[Total Pago],tblCompras[Categoria],$B26,tblCompras[Data],">="&$M$6,tblCompras[Data],"<="&$M$7,tblCompras[Mercado],IF($F$6="(Todos)","*",$F$6)) -> 0
B27: Café | C27: =SUMIFS(tblCompras[Total Pago],tblCompras[Categoria],$B27,tblCompras[Data],">="&$M$6,tblCompras[Data],"<="&$M$7,tblCompras[Mercado],IF($F$6="(Todos)","*",$F$6)) -> 0
... B31: Frutas | C31: =SUMIFS(tblCompras[Total Pago],tblCompras[Categoria],$B31,tblCompras[Data],">="&$M$6,tblCompras[Data],"<="&$M$7,tblCompras[Mercado],IF($F$6="(Todos)","*",$F$6)) -> 0
B32: Total | C32: =SUM(C16:C31) -> 1969.23
B35: EVOLUÇÃO MENSAL
B36: Aplica os filtros de categoria e mercado
B38: Mês/Ano | C38: Total
B39: =IF(Listas!E6="","",Listas!E6) -> mai/2026 | C39: =IF($B39="","",SUMIFS(tblCompras[Total Pago],tblCompras[Data],">="&Listas!$H$6,tblCompras[Data],"<="&EOMONTH(Listas!$H$6,0),tblCompras[Categoria],IF($D$6="(Todos)","*",$D$6),tblCompras[Mercado],IF($F$6="(Todos)","*",$F$6))) -> 2153.03
B40: =IF(Listas!E7="","",Listas!E7) -> jun/2026 | C40: =IF($B40="","",SUMIFS(tblCompras[Total Pago],tblCompras[Data],">="&Listas!$H$7,tblCompras[Data],"<="&EOMONTH(Listas!$H$7,0),tblCompras[Categoria],IF($D$6="(Todos)","*",$D$6),tblCompras[Mercado],IF($F$6="(Todos)","*",$F$6))) -> 1585.03
B41: =IF(Listas!E8="","",Listas!E8) -> jul/2026 | C41: =IF($B41="","",SUMIFS(tblCompras[Total Pago],tblCompras[Data],">="&Listas!$H$8,tblCompras[Data],"<="&EOMONTH(Listas!$H$8,0),tblCompras[Categoria],IF($D$6="(Todos)","*",$D$6),tblCompras[Mercado],IF($F$6="(Todos)","*",$F$6))) -> 1969.23
B42: =IF(Listas!E9="","",Listas!E9) -> ago/2026 | C42: =IF($B42="","",SUMIFS(tblCompras[Total Pago],tblCompras[Data],">="&Listas!$H$9,tblCompras[Data],"<="&EOMONTH(Listas!$H$9,0),tblCompras[Categoria],IF($D$6="(Todos)","*",$D$6),tblCompras[Mercado],IF($F$6="(Todos)","*",$F$6))) -> 255.93
B43: =IF(Listas!E10="","",Listas!E10) | C43: =IF($B43="","",SUMIFS(tblCompras[Total Pago],tblCompras[Data],">="&Listas!$H$10,tblCompras[Data],"<="&EOMONTH(Listas!$H$10,0),tblCompras[Categoria],IF($D$6="(Todos)","*",$D$6),tblCompras[Mercado],IF($F$6="(Todos)","*",$F$6)))
B44: =IF(Listas!E11="","",Listas!E11) | C44: =IF($B44="","",SUMIFS(tblCompras[Total Pago],tblCompras[Data],">="&Listas!$H$11,tblCompras[Data],"<="&EOMONTH(Listas!$H$11,0),tblCompras[Categoria],IF($D$6="(Todos)","*",$D$6),tblCompras[Mercado],IF($F$6="(Todos)","*",$F$6)))
B45: =IF(Listas!E12="","",Listas!E12) | C45: =IF($B45="","",SUMIFS(tblCompras[Total Pago],tblCompras[Data],">="&Listas!$H$12,tblCompras[Data],"<="&EOMONTH(Listas!$H$12,0),tblCompras[Categoria],IF($D$6="(Todos)","*",$D$6),tblCompras[Mercado],IF($F$6="(Todos)","*",$F$6)))
B46: =IF(Listas!E13="","",Listas!E13) | C46: =IF($B46="","",SUMIFS(tblCompras[Total Pago],tblCompras[Data],">="&Listas!$H$13,tblCompras[Data],"<="&EOMONTH(Listas!$H$13,0),tblCompras[Categoria],IF($D$6="(Todos)","*",$D$6),tblCompras[Mercado],IF($F$6="(Todos)","*",$F$6)))
B47: =IF(Listas!E14="","",Listas!E14) | C47: =IF($B47="","",SUMIFS(tblCompras[Total Pago],tblCompras[Data],">="&Listas!$H$14,tblCompras[Data],"<="&EOMONTH(Listas!$H$14,0),tblCompras[Categoria],IF($D$6="(Todos)","*",$D$6),tblCompras[Mercado],IF($F$6="(Todos)","*",$F$6)))
B48: =IF(Listas!E15="","",Listas!E15) | C48: =IF($B48="","",SUMIFS(tblCompras[Total Pago],tblCompras[Data],">="&Listas!$H$15,tblCompras[Data],"<="&EOMONTH(Listas!$H$15,0),tblCompras[Categoria],IF($D$6="(Todos)","*",$D$6),tblCompras[Mercado],IF($F$6="(Todos)","*",$F$6)))
B49: =IF(Listas!E16="","",Listas!E16) | C49: =IF($B49="","",SUMIFS(tblCompras[Total Pago],tblCompras[Data],">="&Listas!$H$16,tblCompras[Data],"<="&EOMONTH(Listas!$H$16,0),tblCompras[Categoria],IF($D$6="(Todos)","*",$D$6),tblCompras[Mercado],IF($F$6="(Todos)","*",$F$6)))
B50: =IF(Listas!E17="","",Listas!E17) | C50: =IF($B50="","",SUMIFS(tblCompras[Total Pago],tblCompras[Data],">="&Listas!$H$17,tblCompras[Data],"<="&EOMONTH(Listas!$H$17,0),tblCompras[Categoria],IF($D$6="(Todos)","*",$D$6),tblCompras[Mercado],IF($F$6="(Todos)","*",$F$6)))
B51: Total | C51: =SUM(C39:C50) -> 5963.22
B54: GASTO POR MERCADO
B55: Aplica os filtros de mês e categoria
B57: Mercado | C57: Total
B58: Supermercados Nori | C58: =SUMIFS(tblCompras[Total Pago],tblCompras[Mercado],$B58,tblCompras[Data],">="&$M$6,tblCompras[Data],"<="&$M$7,tblCompras[Categoria],IF($D$6="(Todos)","*",$D$6)) -> 1170.18
B59: Supermercado Canesin | C59: =SUMIFS(tblCompras[Total Pago],tblCompras[Mercado],$B59,tblCompras[Data],">="&$M$6,tblCompras[Data],"<="&$M$7,tblCompras[Categoria],IF($D$6="(Todos)","*",$D$6)) -> 585.44
B60: Varejao Monteverde | C60: =SUMIFS(tblCompras[Total Pago],tblCompras[Mercado],$B60,tblCompras[Data],">="&$M$6,tblCompras[Data],"<="&$M$7,tblCompras[Categoria],IF($D$6="(Todos)","*",$D$6)) -> 135.86
B61: Andre Eduardo Hipolito | C61: =SUMIFS(tblCompras[Total Pago],tblCompras[Mercado],$B61,tblCompras[Data],">="&$M$6,tblCompras[Data],"<="&$M$7,tblCompras[Categoria],IF($D$6="(Todos)","*",$D$6)) -> 61.27
B62: Varejao Nova Brasil | C62: =SUMIFS(tblCompras[Total Pago],tblCompras[Mercado],$B62,tblCompras[Data],">="&$M$6,tblCompras[Data],"<="&$M$7,tblCompras[Categoria],IF($D$6="(Todos)","*",$D$6)) -> 16.48
B63: Casa de Carnes Barao da Carne | C63: =SUMIFS(tblCompras[Total Pago],tblCompras[Mercado],$B63,tblCompras[Data],">="&$M$6,tblCompras[Data],"<="&$M$7,tblCompras[Categoria],IF($D$6="(Todos)","*",$D$6)) -> 0
B64: Lanchoti e Martins | C64: =SUMIFS(tblCompras[Total Pago],tblCompras[Mercado],$B64,tblCompras[Data],">="&$M$6,tblCompras[Data],"<="&$M$7,tblCompras[Categoria],IF($D$6="(Todos)","*",$D$6)) -> 0
B65: Andre Novato Ribeiro | C65: =SUMIFS(tblCompras[Total Pago],tblCompras[Mercado],$B65,tblCompras[Data],">="&$M$6,tblCompras[Data],"<="&$M$7,tblCompras[Categoria],IF($D$6="(Todos)","*",$D$6)) -> 0
B66: Real Atacamix | C66: =SUMIFS(tblCompras[Total Pago],tblCompras[Mercado],$B66,tblCompras[Data],">="&$M$6,tblCompras[Data],"<="&$M$7,tblCompras[Categoria],IF($D$6="(Todos)","*",$D$6)) -> 0
B67: Crystal | C67: =SUMIFS(tblCompras[Total Pago],tblCompras[Mercado],$B67,tblCompras[Data],">="&$M$6,tblCompras[Data],"<="&$M$7,tblCompras[Categoria],IF($D$6="(Todos)","*",$D$6)) -> 0
B68: André | C68: =SUMIFS(tblCompras[Total Pago],tblCompras[Mercado],$B68,tblCompras[Data],">="&$M$6,tblCompras[Data],"<="&$M$7,tblCompras[Categoria],IF($D$6="(Todos)","*",$D$6)) -> 0
B69: Andre Supermercado | C69: =SUMIFS(tblCompras[Total Pago],tblCompras[Mercado],$B69,tblCompras[Data],">="&$M$6,tblCompras[Data],"<="&$M$7,tblCompras[Categoria],IF($D$6="(Todos)","*",$D$6)) -> 0
B70: Canesin | C70: =SUMIFS(tblCompras[Total Pago],tblCompras[Mercado],$B70,tblCompras[Data],">="&$M$6,tblCompras[Data],"<="&$M$7,tblCompras[Categoria],IF($D$6="(Todos)","*",$D$6)) -> 0
B71: Total | C71: =SUM(C58:C70) -> 1969.23

Sheet Nota Fiscal
B2: NOTAS FISCAIS — CONFERÊNCIA
B3: Uma nota = um bloco no padrão fixo. Soma, diferença e status são fórmulas: basta digitar os itens e o total do cupom.
B4: Para lançar uma nota nova: copie o BLOCO MODELO inteiro (da barra do título até a linha em branco), cole no fim da aba e preencha as células amarelas.
B5: Lembrete: os itens também precisam ser lançados na aba Compras — é ela que alimenta o Painel e a Análise Dinâmica.
B7: ÍNDICE DAS NOTAS
B8: Resumo automático — clique no nº para ir até a nota
B10: Nº | C10: Data | D10: Mercado | E10: Documento | F10: Pagamento | G10: Itens | H10: Total oficial | I10: Soma itens | J10: Dif. (R$) | K10: Status
B11: 001 | C11: =C103 -> 46144 | D11: =C102 -> Crystal | E11: =G102 -> NFC-e 000052920 série 017 | F11: =G103 -> Cartão de Crédito | G11: =C105 -> 3 | H11: =G104 -> 27.67 | I11: =G105 -> 27.67 | J11: =G106 -> 0 | K11: =IF(AND(OR(C104="",C104=C105,C104=C106),ABS(N(G106))<=0.05),"OK","Revisar") -> OK
B12: 002 | C12: =C115 -> 46146 | D12: =C114 -> Supermercados Nori | E12: =G114 -> Cupom 00077650 / NFC-e 24610 Série 004 | F12: =G115 -> Cartão de Crédito | G12: =C117 -> 21 | H12: =G116 -> 184.05 | I12: =G117 -> 184.05 | J12: =G118 -> 0 | K12: =IF(AND(OR(C116="",C116=C117,C116=C118),ABS(N(G118))<=0.05),"OK","Revisar") -> OK
B13: 003 | C13: =C145 -> 46147 | D13: =C144 -> Supermercados Nori | E13: =G144 -> Cupom 91475 | F13: =G145 -> Cartão de Crédito | G13: =C147 -> 33 | H13: =G146 -> 301.86 | I13: =G147 -> 301.76 | J13: =G148 -> 0.1 | K13: =IF(AND(OR(C146="",C146=C147,C146=C148),ABS(N(G148))<=0.05),"OK","Revisar") -> Revisar
B14: 004 | C14: =C187 -> 46148 | D14: =C186 -> Varejao Monteverde | E14: =G186 -> NFC-e 2410 série 2 | F14: =G187 -> Cartão de Crédito | G14: =C189 -> 3 | H14: =G188 -> 17.69 | I14: =G189 -> 17.69 | J14: =G190 -> 0 | K14: =IF(AND(OR(C188="",C188=C189,C188=C190),ABS(N(G190))<=0.05),"OK","Revisar") -> OK
B15: 005 | C15: =C199 -> 46151 | D15: =C198 -> Supermercado Canesin | E15: =G198 -> NFC-e 000038274 série 301 | F15: =G199 -> Cartão de Crédito | G15: =C201 -> 2 | H15: =G200 -> 16.18 | I15: =G201 -> 16.18 | J15: =G202 -> 0 | K15: =IF(AND(OR(C200="",C200=C201,C200=C202),ABS(N(G202))<=0.05),"OK","Revisar") -> OK
B16: 006 | C16: =C210 -> 46152 | D16: =C209 -> Casa de Carnes Barao da Carne | E16: =G209 -> Pedido 083825 (Orçamento - Sem Valor Fiscal) | F16: =G210 -> Cartão de Crédito | G16: =C212 -> 2 | H16: =G211 -> 78.48 | I16: =G212 -> 78.48 | J16: =G213 -> 0 | K16: =IF(AND(OR(C211="",C211=C212,C211=C213),ABS(N(G213))<=0.05),"OK","Revisar") -> OK
B17: 007 | C17: =C221 -> 46152 | D17: =C220 -> Varejao Monteverde | E17: =G220 -> NFC-e 8933 série 1 | F17: =G221 -> Cartão de Crédito | G17: =C223 -> 2 | H17: =G222 -> 13.73 | I17: =G223 -> 13.73 | J17: =G224 -> 0 | K17: =IF(AND(OR(C222="",C222=C223,C222=C224),ABS(N(G224))<=0.05),"OK","Revisar") -> OK
B18: 008 | C18: =C232 -> 46152 | D18: =C231 -> Real Atacamix | E18: =G231 -> Pedido 103009583 Oper. 03 | F18: =G232 -> Cartão de Crédito | G18: =C234 -> 3 | H18: =G233 -> 39.96 | I18: =G234 -> 39.96 | J18: =G235 -> 0 | K18: =IF(AND(OR(C233="",C233=C234,C233=C235),ABS(N(G235))<=0.05),"OK","Revisar") -> OK
B19: 009 | C19: =C244 -> 46152 | D19: =C243 -> Andre Supermercado | E19: =G243 -> Cupom 0900212 PDV 03 | F19: =G244 -> Cartão de Crédito | G19: =C246 -> 3 | H19: =G245 -> 18.18 | I19: =G246 -> 18.18 | J19: =G247 -> 0 | K19: =IF(AND(OR(C245="",C245=C246,C245=C247),ABS(N(G247))<=0.05),"OK","Revisar") -> OK
B20: 010 | C20: =C256 -> 46152 | D20: =C255 -> Supermercados Nori | E20: =G255 -> Cupom 00083585 NFC-e 27580 Serie 014 | F20: =G256 -> PIX | G20: =C258 -> 3 | H20: =G257 -> 93.46 | I20: =G258 -> 93.46 | J20: =G259 -> 0 | K20: =IF(AND(OR(C257="",C257=C258,C257=C259),ABS(N(G259))<=0.05),"OK","Revisar") -> OK
B21: 011 | C21: =C268 -> 46156 | D21: =C267 -> Andre Novato Ribeiro | E21: =G267 -> Cupom Nota 36741 | F21: =G268 -> Cartão de Crédito | G21: =C270 -> 2 | H21: =G269 -> 39.98 | I21: =G270 -> 39.98 | J21: =G271 -> 0 | K21: =IF(AND(OR(C269="",C269=C270,C269=C271),ABS(N(G271))<=0.05),"OK","Revisar") -> OK
B22: 012 | C22: =C279 -> 46156 | D22: =C278 -> Varejao Monteverde | E22: =G278 -> Cupom NFC-e 3067 Série 3 | F22: =G279 -> Cartão de Crédito | G22: =C281 -> 4 | H22: =G280 -> 30.83 | I22: =G281 -> 30.83 | J22: =G282 -> 0 | K22: =IF(AND(OR(C280="",C280=C281,C280=C282),ABS(N(G282))<=0.05),"OK","Revisar") -> OK
B23: 013 | C23: =C292 -> 46157 | D23: =C291 -> Supermercados Nori | E23: =G291 -> Cupom Cupom 00065290 | F23: =G292 -> Cartão de Crédito | G23: =C294 -> 50 | H23: =G293 -> 370.63 | I23: =G294 -> 370.63 | J23: =G295 -> 0 | K23: =IF(AND(OR(C293="",C293=C294,C293=C295),ABS(N(G295))<=0.05),"OK","Revisar") -> OK
B24: 014 | C24: =C351 -> 46158 | D24: =C350 -> Varejao Nova Brasil | E24: =G350 -> Cupom Não Fiscal - Terminal 0002 - Vitoria | F24: =G351 -> Não informado | G24: =C353 -> 5 | H24: =G352 -> 48.52 | I24: =G353 -> 48.52 | J24: =G354 -> 0 | K24: =IF(AND(OR(C352="",C352=C353,C352=C354),ABS(N(G354))<=0.05),"OK","Revisar") -> OK
B25: 015 | C25: =C365 -> 46159 | D25: =C364 -> Supermercados Nori | E25: =G364 -> Cupom 00071051 NFC-e 22022 Série 007 | F25: =G365 -> Cartão de Crédito | G25: =C367 -> 9 | H25: =G366 -> 102.74 | I25: =G367 -> 102.74 | J25: =G368 -> 0 | K25: =IF(AND(OR(C366="",C366=C367,C366=C368),ABS(N(G368))<=0.05),"OK","Revisar") -> OK
B26: 016 | C26: =C383 -> 46161 | D26: =C382 -> Supermercado Canesin | E26: =G382 -> Cupom (NFC-e) 000050028 / Série 302 | F26: =G383 -> Cartão de Crédito | G26: =C385 -> 2 | H26: =G384 -> 17.05 | I26: =G385 -> 17.05 | J26: =G386 -> 0 | K26: =IF(AND(OR(C384="",C384=C385,C384=C386),ABS(N(G386))<=0.05),"OK","Revisar") -> OK
B27: 017 | C27: =C394 -> 46162 | D27: =C393 -> Andre Eduardo Hipolito | E27: =G393 -> Cupom DOC 038073 / COO 036256 (não fiscal) | F27: =G394 -> Cartão de Crédito | G27: =C396 -> 4 | H27: =G395 -> 36 | I27: =G396 -> 36 | J27: =G397 -> 0 | K27: =IF(AND(OR(C395="",C395=C396,C395=C397),ABS(N(G397))<=0.05),"OK","Revisar") -> OK
B28: 018 | C28: =C407 -> 46163 | D28: =C406 -> Varejao Monteverde | E28: =G406 -> Cupom NFC-e nº 3243 / Série 3 | F28: =G407 -> Cartão de Crédito | G28: =C409 -> 5 | H28: =G408 -> 33.34 | I28: =G409 -> 33.34 | J28: =G410 -> 0 | K28: =IF(AND(OR(C408="",C408=C409,C408=C410),ABS(N(G410))<=0.05),"OK","Revisar") -> OK
B29: 019 | C29: =C421 -> 46168 | D29: =C420 -> Varejao Monteverde | E29: =G420 -> Cupom COD: 1492272 PDV1 | F29: =G421 -> Dinheiro | G29: =C423 -> 5 | H29: =G422 -> 33.25 | I29: =G423 -> 33.25 | J29: =G424 -> 0 | K29: =IF(AND(OR(C422="",C422=C423,C422=C424),ABS(N(G424))<=0.05),"OK","Revisar") -> OK
B30: 020 | C30: =C435 -> 46168 | D30: =C434 -> Andre Eduardo Hipolito | E30: =G434 -> Cupom NFC-e nº 000002266 / Série 001 / DOC 040187 | F30: =G435 -> Dinheiro | G30: =C437 -> 1 | H30: =G436 -> 5.85 | I30: =G437 -> 5.85 | J30: =G438 -> 0 | K30: =IF(AND(OR(C436="",C436=C437,C436=C438),ABS(N(G438))<=0.05),"OK","Revisar") -> OK
B31: 021 | C31: =C445 -> 46169 | D31: =C444 -> Supermercado Canesin | E31: =G444 -> NFC-e 000042390 — Série 301 | F31: =G445 -> Dinheiro R$ 100,00 / Troco R$ 86,02 | G31: =C447 -> 2 | H31: =G446 -> 13.98 | I31: =G447 -> 13.98 | J31: =G448 -> 0 | K31: =IF(AND(OR(C446="",C446=C447,C446=C448),ABS(N(G448))<=0.05),"OK","Revisar") -> OK
B32: 022 | C32: =C456 -> 46169 | D32: =C455 -> Andre Eduardo Hipolito | E32: =G455 -> Cupom DOC 040540 — COO 040075 | F32: =G456 -> Dinheiro R$ 21,00 / Troco R$ 0,08 | G32: =C458 -> 3 | H32: =G457 -> 20.92 | I32: =G458 -> 20.92 | J32: =G459 -> 0 | K32: =IF(AND(OR(C457="",C457=C458,C457=C459),ABS(N(G459))<=0.05),"OK","Revisar") -> OK
B33: 023 | C33: =C468 -> 46170 | D33: =C467 -> Varejao Monteverde | E33: =G467 -> Cupom COD: 1492588 — PDV1 | F33: =G468 -> Dinheiro R$ 50,55 / Troco R$ 28,00 | G33: =C470 -> 3 | H33: =G469 -> 22.55 | I33: =G470 -> 22.55 | J33: =G471 -> 0 | K33: =IF(AND(OR(C469="",C469=C470,C469=C471),ABS(N(G471))<=0.05),"OK","Revisar") -> OK
B34: 024 | C34: =C480 -> 46171 | D34: =C479 -> Varejao Monteverde | E34: =G479 -> Cupom COD: 1492747 — PDV2 | F34: =G480 -> Dinheiro R$ 17,00 / Troco R$ 0,20 | G34: =C482 -> 1 | H34: =G481 -> 16.8 | I34: =G482 -> 16.8 | J34: =G483 -> 0 | K34: =IF(AND(OR(C481="",C481=C482,C481=C483),ABS(N(G483))<=0.05),"OK","Revisar") -> OK
B35: 025 | C35: =C490 -> 46171 | D35: =C489 -> Supermercado Canesin | E35: =G489 -> Cupom NFC-e nº 52295 / Série 302 | F35: =G490 -> Dinheiro | G35: =C492 -> 12 | H35: =G491 -> 78.21 | I35: =G492 -> 78.21 | J35: =G493 -> 0 | K35: =IF(AND(OR(C491="",C491=C492,C491=C493),ABS(N(G493))<=0.05),"OK","Revisar") -> OK
B36: 026 | C36: =C511 -> 46173 | D36: =C510 -> Supermercados Nori | E36: =G510 -> Cupom Cupom 00073882 | F36: =G511 -> Não informado | G36: =C513 -> 44 | H36: =G512 -> 289.12 | I36: =G513 -> 289.12 | J36: =G514 -> 0 | K36: =IF(AND(OR(C512="",C512=C513,C512=C514),ABS(N(G514))<=0.05),"OK","Revisar") -> OK
B37: 027 | C37: =C564 -> 46173 | D37: =C563 -> Varejao Monteverde | E37: =G563 -> NFC-e NFC-e nº 9592 / Série 1 | F37: =G564 -> Cartão de Crédito | G37: =C566 -> 4 | H37: =G565 -> 23.9 | I37: =G566 -> 23.9 | J37: =G567 -> 0 | K37: =IF(AND(OR(C565="",C565=C566,C565=C567),ABS(N(G567))<=0.05),"OK","Revisar") -> OK
B38: 028 | C38: =C577 -> 46176 | D38: =C576 -> Varejao Monteverde | E38: =G576 -> NFC-e NFC-e nº 3087 / Série 2 | F38: =G577 -> Cartão de Crédito | G38: =C579 -> 13 | H38: =G578 -> 78.38 | I38: =G579 -> 78.38 | J38: =G580 -> 0 | K38: =IF(AND(OR(C578="",C578=C579,C578=C580),ABS(N(G580))<=0.05),"OK","Revisar") -> OK
B39: 029 | C39: =C599 -> 46176 | D39: =C598 -> Supermercados Nori | E39: =G598 -> Cupom / NFC-e Cupom 68001 · NFC-e nº 20926 / Série 005 | F39: =G599 -> Cartão de Crédito | G39: =C601 -> 47 | H39: =G600 -> 336.92 | I39: =G601 -> 336.92 | J39: =G602 -> 0 | K39: =IF(AND(OR(C600="",C600=C601,C600=C602),ABS(N(G602))<=0.05),"OK","Revisar") -> OK
B40: 030 | C40: =C655 -> 46177 | D40: =C654 -> Supermercado Canesin | E40: =G654 -> Cupom (NFC-e) 000053664 / Série 302 | F40: =G655 -> Cartão de Crédito | G40: =C657 -> 5 | H40: =G656 -> 26.73 | I40: =G657 -> 26.73 | J40: =G658 -> 0 | K40: =IF(AND(OR(C656="",C656=C657,C656=C658),ABS(N(G658))<=0.05),"OK","Revisar") -> OK
B41: 031 | C41: =C669 -> 46179 | D41: =C668 -> Supermercados Nori | E41: =G668 -> Cupom (NFC-e) 000034682 / Série 002 (Cupom 00103940) | F41: =G669 -> Cartão de Crédito | G41: =C671 -> 16 | H41: =G670 -> 162.37 | I41: =G671 -> 162.37 | J41: =G672 -> 0 | K41: =IF(AND(OR(C670="",C670=C671,C670=C672),ABS(N(G672))<=0.05),"OK","Revisar") -> OK
B42: 032 | C42: =C694 -> 46183 | D42: =C693 -> Supermercado Canesin | E42: =G693 -> Cupom (NFC-e) 000054990 / Série 302 (Cupom 093663) | F42: =G694 -> Cartão de Crédito | G42: =C696 -> 2 | H42: =G695 -> 15.46 | I42: =G696 -> 15.46 | J42: =G697 -> 0 | K42: =IF(AND(OR(C695="",C695=C696,C695=C697),ABS(N(G697))<=0.05),"OK","Revisar") -> OK
B43: 033 | C43: =C705 -> 46183 | D43: =C704 -> Lanchoti e Martins | E43: =G704 -> Cupom (NFC-e) 000235703 / Série 001 | F43: =G705 -> Cartão de Crédito | G43: =C707 -> 2 | H43: =G706 -> 51.15 | I43: =G707 -> 51.15 | J43: =G708 -> 0 | K43: =IF(AND(OR(C706="",C706=C707,C706=C708),ABS(N(G708))<=0.05),"OK","Revisar") -> OK
B44: 034 | C44: =C716 -> 46185 | D44: =C715 -> Supermercados Nori | E44: =G715 -> Cupom (NFC-e) 00070533 / Série 005 | F44: =G716 -> Cartão de Crédito | G44: =C718 -> 63 | H44: =G717 -> 477.41 | I44: =G718 -> 477.41 | J44: =G719 -> 0 | K44: =IF(AND(OR(C717="",C717=C718,C717=C719),ABS(N(G719))<=0.05),"OK","Revisar") -> Revisar
B45: 035 | C45: =C788 -> 46193 | D45: =C787 -> Supermercados Nori | E45: =G787 -> Cupom (NFC-e) 00083903 / Série 004 | F45: =G788 -> Cartão de Crédito | G45: =C790 -> 19 | H45: =G789 -> 158.19 | I45: =G790 -> 158.19 | J45: =G791 -> 0 | K45: =IF(AND(OR(C789="",C789=C790,C789=C791),ABS(N(G791))<=0.05),"OK","Revisar") -> OK
B46: 036 | C46: =C816 -> 46197 | D46: =C815 -> Supermercado Canesin | E46: =G815 -> Cupom (NFC-e) 00048969 / Série 301 | F46: =G816 -> Cartão de Crédito | G46: =C818 -> 2 | H46: =G817 -> 10.94 | I46: =G818 -> 10.94 | J46: =G819 -> 0 | K46: =IF(AND(OR(C817="",C817=C818,C817=C819),ABS(N(G819))<=0.05),"OK","Revisar") -> OK
B47: 037 | C47: =C827 -> 46199 | D47: =C826 -> Supermercado Canesin | E47: =G826 -> Cupom (NFC-e) 00049425 / Série 301 | F47: =G827 -> Cartão de Crédito | G47: =C829 -> 4 | H47: =G828 -> 34.14 | I47: =G829 -> 34.14 | J47: =G830 -> 0 | K47: =IF(AND(OR(C828="",C828=C829,C828=C830),ABS(N(G830))<=0.05),"OK","Revisar") -> OK
B48: 038 | C48: =C840 -> 46200 | D48: =C839 -> Varejao Monteverde | E48: =G839 -> Cupom (NFC-e) 00003965 / Série 003 | F48: =G840 -> Cartão de Crédito | G48: =C842 -> 8 | H48: =G841 -> 43.91 | I48: =G842 -> 43.91 | J48: =G843 -> 0 | K48: =IF(AND(OR(C841="",C841=C842,C841=C843),ABS(N(G843))<=0.05),"OK","Revisar") -> OK
B49: 039 | C49: =C857 -> 46204 | D49: =C856 -> Supermercado Canesin | E49: =G856 -> Cupom (NFC-e) 000059513 / Série 302 | F49: =G857 -> Cartão de Crédito | G49: =C859 -> 3 | H49: =G858 -> 27.79 | I49: =G859 -> 27.79 | J49: =G860 -> 0 | K49: =IF(AND(OR(C858="",C858=C859,C858=C860),ABS(N(G860))<=0.05),"OK","Revisar") -> OK
B50: 040 | C50: =C869 -> 46204 | D50: =C868 -> Supermercado Canesin | E50: =G868 -> Cupom (NFC-e) 000050582 / Série 301 | F50: =G869 -> Cartão de Crédito | G50: =C871 -> 6 | H50: =G870 -> 47.24 | I50: =G871 -> 47.24 | J50: =G872 -> 0 | K50: =IF(AND(OR(C870="",C870=C871,C870=C872),ABS(N(G872))<=0.05),"OK","Revisar") -> OK
B51: 041 | C51: =C884 -> 46205 | D51: =C883 -> Andre Eduardo Hipolito | E51: =G883 -> Cupom (NFC-e) DOC 050716 | F51: =G884 -> Cartão de Crédito | G51: =C886 -> 4 | H51: =G885 -> 20.73 | I51: =G886 -> 20.73 | J51: =G887 -> 0 | K51: =IF(AND(OR(C885="",C885=C886,C885=C887),ABS(N(G887))<=0.05),"OK","Revisar") -> OK
B52: 042 | C52: =C897 -> 46207 | D52: =C896 -> Supermercados Nori | E52: =G896 -> Cupom (NFC-e) 96224 | F52: =G897 -> Cartão de Crédito | G52: =C899 -> 74 | H52: =G898 -> 502.56 | I52: =G899 -> 503.18 | J52: =G900 -> -0.62 | K52: =IF(AND(OR(C898="",C898=C899,C898=C900),ABS(N(G900))<=0.05),"OK","Revisar") -> Revisar
B53: 043 | C53: =C980 -> 46207 | D53: =C979 -> Varejao Monteverde | E53: =G979 -> Cupom (NFC-e) 000004121 / Série 3 | F53: =G980 -> Cartão de Crédito | G53: =C982 -> 3 | H53: =G981 -> 24.72 | I53: =G982 -> 24.72 | J53: =G983 -> 0 | K53: =IF(AND(OR(C981="",C981=C982,C981=C983),ABS(N(G983))<=0.05),"OK","Revisar") -> OK
B54: 044 | C54: =C992 -> 46208 | D54: =C991 -> Supermercados Nori | E54: =G991 -> Cupom 00046948 / Série 008 | F54: =G992 -> Cartão de Crédito | G54: =C994 -> 7 | H54: =G993 -> 74.35 | I54: =G994 -> 74.35 | J54: =G995 -> 0 | K54: =IF(AND(OR(C993="",C993=C994,C993=C995),ABS(N(G995))<=0.05),"OK","Revisar") -> OK
B55: 045 | C55: =C1008 -> 46209 | D55: =C1007 -> Varejao Monteverde | E55: =G1007 -> Cupom (NFC-e) 000004161 / Série 3 | F55: =G1008 -> Cartão de Crédito | G55: =C1010 -> 2 | H55: =G1009 -> 10.08 | I55: =G1010 -> 10.08 | J55: =G1011 -> 0 | K55: =IF(AND(OR(C1009="",C1009=C1010,C1009=C1011),ABS(N(G1011))<=0.05),"OK","Revisar") -> OK
B56: 046 | C56: =C1019 -> 46209 | D56: =C1018 -> Supermercado Canesin | E56: =G1018 -> Cupom (NFC-e) 000051984 / Série 301 | F56: =G1019 -> Cartão de Crédito | G56: =C1021 -> 3 | H56: =G1020 -> 35 | I56: =G1021 -> 35 | J56: =G1022 -> 0 | K56: =IF(AND(OR(C1020="",C1020=C1021,C1020=C1022),ABS(N(G1022))<=0.05),"OK","Revisar") -> OK
B57: 047 | C57: =C1031 -> 46210 | D57: =C1030 -> Supermercados Nori | E57: =G1030 -> Cupom 00097350 / Série 003 | F57: =G1031 -> Cartão de Crédito | G57: =C1033 -> 20 | H57: =G1032 -> 192.25 | I57: =G1033 -> 192.25 | J57: =G1034 -> 0 | K57: =IF(AND(OR(C1032="",C1032=C1033,C1032=C1034),ABS(N(G1034))<=0.05),"OK","Revisar") -> OK
B58: 048 | C58: =C1060 -> 46212 | D58: =C1059 -> Supermercados Nori | E58: =G1059 -> Cupom 00074873 / Série 005 | F58: =G1060 -> Cartão de Crédito | G58: =C1062 -> 24 | H58: =G1061 -> 265.82 | I58: =G1062 -> 265.82 | J58: =G1063 -> 0 | K58: =IF(AND(OR(C1061="",C1061=C1062,C1061=C1063),ABS(N(G1063))<=0.05),"OK","Revisar") -> OK
B59: 049 | C59: =C1093 -> 46215 | D59: =C1092 -> Supermercados Nori | E59: =G1092 -> Cupom 00050006 / Série 011 | F59: =G1093 -> Cartão de Crédito | G59: =C1095 -> 13 | H59: =G1094 -> 134.58 | I59: =G1095 -> 134.58 | J59: =G1096 -> 0 | K59: =IF(AND(OR(C1094="",C1094=C1095,C1094=C1096),ABS(N(G1096))<=0.05),"OK","Revisar") -> OK
B60: 050 | C60: =C1115 -> 46217 | D60: =C1114 -> Varejao Monteverde | E60: =G1114 -> Cupom 4194 / Série 002 | F60: =G1115 -> Cartão de Crédito | G60: =C1117 -> 3 | H60: =G1116 -> 23.31 | I60: =G1117 -> 23.31 | J60: =G1118 -> 0 | K60: =IF(AND(OR(C1116="",C1116=C1117,C1116=C1118),ABS(N(G1118))<=0.05),"OK","Revisar") -> OK
B61: 051 | C61: =C1127 -> 46217 | D61: =C1126 -> Supermercado Canesin | E61: =G1126 -> Cupom 053763 / Série 301 | F61: =G1127 -> Cartão de Crédito | G61: =C1129 -> 5 | H61: =G1128 -> 67.69 | I61: =G1129 -> 67.69 | J61: =G1130 -> 0 | K61: =IF(AND(OR(C1128="",C1128=C1129,C1128=C1130),ABS(N(G1130))<=0.05),"OK","Revisar") -> OK
B62: 052 | C62: =C1141 -> 46220 | D62: =C1140 -> Varejao Monteverde | E62: =G1140 -> Cupom 1500598 / PDV3 | F62: =G1141 -> Dinheiro | G62: =C1143 -> 4 | H62: =G1142 -> 32.49 | I62: =G1143 -> 32.49 | J62: =G1144 -> 0 | K62: =IF(AND(OR(C1142="",C1142=C1143,C1142=C1144),ABS(N(G1144))<=0.05),"OK","Revisar") -> OK
B63: 053 | C63: =C1154 -> 46220 | D63: =C1153 -> Andre Eduardo Hipolito | E63: =G1153 -> Cupom 54527 | F63: =G1154 -> Dinheiro | G63: =C1156 -> 2 | H63: =G1155 -> 21 | I63: =G1156 -> 21 | J63: =G1157 -> 0 | K63: =IF(AND(OR(C1155="",C1155=C1156,C1155=C1157),ABS(N(G1157))<=0.05),"OK","Revisar") -> OK
B64: 054 | C64: =C1165 -> 46222 | D64: =C1164 -> Varejao Monteverde | E64: =G1164 -> Cupom 1500813 / PDV2 | F64: =G1165 -> Dinheiro | G64: =C1167 -> 1 | H64: =G1166 -> 2.59 | I64: =G1167 -> 2.59 | J64: =G1168 -> 0 | K64: =IF(AND(OR(C1166="",C1166=C1167,C1166=C1168),ABS(N(G1168))<=0.05),"OK","Revisar") -> OK
B65: 055 | C65: =C1175 -> 46222 | D65: =C1174 -> Varejao Nova Brasil | E65: =G1174 -> Cupom 002286 / Série 002 | F65: =G1175 -> Dinheiro | G65: =C1177 -> 1 | H65: =G1176 -> 16.48 | I65: =G1177 -> 16.48 | J65: =G1178 -> 0 | K65: =IF(AND(OR(C1176="",C1176=C1177,C1176=C1178),ABS(N(G1178))<=0.05),"OK","Revisar") -> OK
B66: 056 | C66: =C1185 -> 46222 | D66: =C1184 -> Supermercado Canesin | E66: =G1184 -> Cupom 055105 / Série 301 | F66: =G1185 -> Dinheiro | G66: =C1187 -> 5 | H66: =G1186 -> 37.35 | I66: =G1187 -> 37.35 | J66: =G1188 -> 0 | K66: =IF(AND(OR(C1186="",C1186=C1187,C1186=C1188),ABS(N(G1188))<=0.05),"OK","Revisar") -> OK
B67: 057 | C67: =C1199 -> 46223 | D67: =C1198 -> Varejao Monteverde | E67: =G1198 -> Cupom 1500960 / PDV1 | F67: =G1199 -> Dinheiro | G67: =C1201 -> 1 | H67: =G1200 -> 16.8 | I67: =G1201 -> 16.8 | J67: =G1202 -> 0 | K67: =IF(AND(OR(C1200="",C1200=C1201,C1200=C1202),ABS(N(G1202))<=0.05),"OK","Revisar") -> OK
B68: 058 | C68: =C1209 -> 46223 | D68: =C1208 -> Andre Eduardo Hipolito | E68: =G1208 -> Cupom 055348 | F68: =G1209 -> Cartão de Crédito | G68: =C1211 -> 3 | H68: =G1210 -> 19.54 | I68: =G1211 -> 19.54 | J68: =G1212 -> 0 | K68: =IF(AND(OR(C1210="",C1210=C1211,C1210=C1212),ABS(N(G1212))<=0.05),"OK","Revisar") -> OK
B69: 059 | C69: =C1221 -> 46226 | D69: =C1220 -> Varejao Monteverde | E69: =G1220 -> NFC-e 4449 / Série 002 | F69: =G1221 -> Cartão de Crédito | G69: =C1223 -> 5 | H69: =G1222 -> 25.87 | I69: =G1223 -> 25.87 | J69: =G1224 -> 0 | K69: =IF(AND(OR(C1222="",C1222=C1223,C1222=C1224),ABS(N(G1224))<=0.05),"OK","Revisar") -> OK
B70: 060 | C70: =C1235 -> 46226 | D70: =C1234 -> Supermercado Canesin | E70: =G1234 -> NFC-e Série 302 (nº não visível no cupom) | F70: =G1235 -> Prazo | G70: =C1237 -> 10 | H70: =G1236 -> 76.56 | I70: =G1237 -> 76.56 | J70: =G1238 -> 0 | K70: =IF(AND(OR(C1236="",C1236=C1237,C1236=C1238),ABS(N(G1238))<=0.05),"OK","Revisar") -> OK
B71: 061 | C71: =C1254 -> 46228 | D71: =C1253 -> Supermercado Canesin | E71: =G1253 -> NFC-e 000056380 / Série 301 | F71: =G1254 -> Prazo | G71: =C1256 -> 17 | H71: =G1255 -> 108.78 | I71: =G1256 -> 108.78 | J71: =G1257 -> 0 | K71: =IF(AND(OR(C1255="",C1255=C1256,C1255=C1257),ABS(N(G1257))<=0.05),"OK","Revisar") -> OK
B72: 062 | C72: =C1280 -> 46229 | D72: =C1279 -> Supermercado Canesin | E72: =G1279 -> NFC-e 000030471 / Série 303 | F72: =G1280 -> Dinheiro | G72: =C1282 -> 3 | H72: =G1281 -> 48.96 | I72: =G1282 -> 48.96 | J72: =G1283 -> 0 | K72: =IF(AND(OR(C1281="",C1281=C1282,C1281=C1283),ABS(N(G1283))<=0.05),"OK","Revisar") -> OK
B73: 063 | C73: =C1292 -> 46230 | D73: =C1291 -> Supermercado Canesin | E73: =G1291 -> NFC-e 000064856 / Série 302 | F73: =G1292 -> Cartão de Crédito | G73: =C1294 -> 4 | H73: =G1293 -> 39.27 | I73: =G1294 -> 39.27 | J73: =G1295 -> 0 | K73: =IF(AND(OR(C1293="",C1293=C1294,C1293=C1295),ABS(N(G1295))<=0.05),"OK","Revisar") -> OK
B74: 064 | C74: =C1305 -> 46231 | D74: =C1304 -> Supermercado Canesin | E74: =G1304 -> NFC-e 000064994 / Série 302 | F74: =G1305 -> Débito | G74: =C1307 -> 4 | H74: =G1306 -> 20.67 | I74: =G1307 -> 20.67 | J74: =G1308 -> 0 | K74: =IF(AND(OR(C1306="",C1306=C1307,C1306=C1308),ABS(N(G1308))<=0.05),"OK","Revisar") -> OK
B75: 065 | C75: =C1318 -> 46232 | D75: =C1317 -> Supermercado Canesin | E75: =G1317 -> NFC-e 000057380 / Série 301 | F75: =G1318 -> Débito | G75: =C1320 -> 5 | H75: =G1319 -> 48.4 | I75: =G1320 -> 48.4 | J75: =G1321 -> 0 | K75: =IF(AND(OR(C1319="",C1319=C1320,C1319=C1321),ABS(N(G1321))<=0.05),"OK","Revisar") -> OK
B76: 066 | C76: =C1332 -> 46233 | D76: =C1331 -> Supermercado Canesin | E76: =G1331 -> NFC-e 000065542 / Série 302 | F76: =G1332 -> Débito | G76: =C1334 -> 2 | H76: =G1333 -> 27.73 | I76: =G1334 -> 27.73 | J76: =G1335 -> 0 | K76: =IF(AND(OR(C1333="",C1333=C1334,C1333=C1335),ABS(N(G1335))<=0.05),"OK","Revisar") -> OK
B77: 067 | C77: =C1343 -> 46237 | D77: =C1342 -> Supermercado Canesin | E77: =G1342 -> NFC-e 000066429 / Série 302 | F77: =G1343 -> Débito | G77: =C1345 -> 3 | H77: =G1344 -> 33.35 | I77: =G1345 -> 33.35 | J77: =G1346 -> 0 | K77: =IF(AND(OR(C1344="",C1344=C1345,C1344=C1346),ABS(N(G1346))<=0.05),"OK","Revisar") -> OK
B78: 068 | C78: =C1355 -> 46239 | D78: =C1354 -> Supermercado Canesin | E78: =G1354 -> NFC-e 000059085 / Série 301 | F78: =G1355 -> Débito | G78: =C1357 -> 6 | H78: =G1356 -> 55.75 | I78: =G1357 -> 55.75 | J78: =G1358 -> 0 | K78: =IF(AND(OR(C1356="",C1356=C1357,C1356=C1358),ABS(N(G1358))<=0.05),"OK","Revisar") -> OK
B79: 069 | C79: =C1370 -> 46240 | D79: =C1369 -> Supermercado Canesin | E79: =G1369 -> NFC-e 000059425 / Série 301 | F79: =G1370 -> Débito | G79: =C1372 -> 4 | H79: =G1371 -> 49.26 | I79: =G1372 -> 49.26 | J79: =G1373 -> 0 | K79: =IF(AND(OR(C1371="",C1371=C1372,C1371=C1373),ABS(N(G1373))<=0.05),"OK","Revisar") -> OK
B80: 070 | C80: =C1383 -> 46243 | D80: =C1382 -> Supermercados Nori | E80: =G1382 -> Cupom 00053519 / NFC-e 015626 Série 008 | F80: =G1383 -> Débito | G80: =C1385 -> 10 | H80: =G1384 -> 104.29 | I80: =G1385 -> 104.29 | J80: =G1386 -> 0 | K80: =IF(AND(OR(C1384="",C1384=C1385,C1384=C1386),ABS(N(G1386))<=0.05),"OK","Revisar") -> OK
B81: 071 | C81: =C1402 -> 46244 | D81: =C1401 -> Varejao Monteverde | E81: =G1401 -> NFC-e 011275 / Série 1 | F81: =G1402 -> Débito | G81: =C1404 -> 2 | H81: =G1403 -> 13.28 | I81: =G1404 -> 13.28 | J81: =G1405 -> 0 | K81: =IF(AND(OR(C1403="",C1403=C1404,C1403=C1405),ABS(N(G1405))<=0.05),"OK","Revisar") -> OK
D82: Total | G82: =SUM(G11:G81) -> 671 | H82: =SUM(H11:H81) -> 5595.07 | I82: =SUM(I11:I81) -> 5595.59 | J82: =SUM(J11:J81) -> -0.52
B83: BLOCO MODELO — copie este bloco para lançar uma nota nova
B84: Mercado | E84: Documento (cupom/NFC-e)
B85: Data | E85: Pagamento
B86: Qtd. oficial de itens | E86: Total oficial (R$)
B87: Itens lançados (linhas) | C87: =COUNT(H91:H98) -> 0 | E87: Soma dos itens (R$) | G87: =ROUND(SUM(H91:H98),2) -> 0
B88: Unidades lançadas | C88: =ROUND(SUMPRODUCT(((F91:F98="KG")+(F91:F98="G"))*1)+SUMPRODUCT((F91:F98<>"KG")*(F91:F98<>"G")*E91:E98),0) -> 0 | E88: Diferença (R$) | G88: =IF(G86="","",ROUND(G86-G87,2))
B89: Status | C89: =IF(C87=0,"— aguardando lançamento",IF(G86="","SEM TOTAL OFICIAL — informe o total do cupom",IF(AND(OR(C86="",C86=C87,C86=C88),ABS(G88)<=0.05),"FECHADO — itens e valor conferem",IF(ABS(G88)<=0.05,"REVISAR — qtd. de itens não bate","REVISAR — diferença de R$ "&ABS(G88))))) -> — aguardando lançamento | G89: Obs.
B90: Código | C90: Produto | D90: Categoria | E90: Qtd. | F90: Unid. | G90: Preço Unit. | H90: Total | I90: Calc. | J90: Check
I91: =IF(OR(E91="",G91=""),"",ROUND(E91*G91,2)) | J91: =IF(OR(H91="",I91=""),"",IF(ABS(H91-I91)<=0.02,"OK","≠"))
I92: =IF(OR(E92="",G92=""),"",ROUND(E92*G92,2)) | J92: =IF(OR(H92="",I92=""),"",IF(ABS(H92-I92)<=0.02,"OK","≠"))
I93: =IF(OR(E93="",G93=""),"",ROUND(E93*G93,2)) | J93: =IF(OR(H93="",I93=""),"",IF(ABS(H93-I93)<=0.02,"OK","≠"))
I94: =IF(OR(E94="",G94=""),"",ROUND(E94*G94,2)) | J94: =IF(OR(H94="",I94=""),"",IF(ABS(H94-I94)<=0.02,"OK","≠"))
I95: =IF(OR(E95="",G95=""),"",ROUND(E95*G95,2)) | J95: =IF(OR(H95="",I95=""),"",IF(ABS(H95-I95)<=0.02,"OK","≠"))
I96: =IF(OR(E96="",G96=""),"",ROUND(E96*G96,2)) | J96: =IF(OR(H96="",I96=""),"",IF(ABS(H96-I96)<=0.02,"OK","≠"))
I97: =IF(OR(E97="",G97=""),"",ROUND(E97*G97,2)) | J97: =IF(OR(H97="",I97=""),"",IF(ABS(H97-I97)<=0.02,"OK","≠"))
I98: =IF(OR(E98="",G98=""),"",ROUND(E98*G98,2)) | J98: =IF(OR(H98="",I98=""),"",IF(ABS(H98-I98)<=0.02,"OK","≠"))
B101: NOTA 001
B102: Mercado | C102: Crystal | E102: Documento (cupom/NFC-e) | G102: NFC-e 000052920 série 017
B103: Data | C103: 46144 | E103: Pagamento | G103: Cartão de Crédito
B104: Qtd. oficial de itens | C104: 3 | E104: Total oficial (R$) | G104: 27.67
B105: Itens lançados (linhas) | C105: =COUNT(H109:H111) -> 3 | E105: Soma dos itens (R$) | G105: =ROUND(SUM(H109:H111),2) -> 27.67
...

Sheet Compras
A1: Compras
A2: Tabela operacional. Cada linha = um item comprado. Coluna B (Mês/Ano) facilita a comparação entre meses.
A4: Data | B4: Mês/Ano | C4: Mercado | D4: Produto | E4: Categoria | F4: Qtd. | G4: Unid. | H4: Total Pago | I4: Preço Unit. | J4: Origem | K4: Obs.
A5: 46147 | B5: =TEXT(A5,"mmm/aaaa") -> Iyar/Tuesday | C5: Supermercados Nori | D5: IOGURTE VOVO ANIZIA | E5: Laticinios | F5: 1 | G5: UN | H5: 10.8 | I5: =IFERROR(H5/F5,0) -> 10.8 | J5: Cupom 00091475
A6: 46147 | B6: =TEXT(A6,"mmm/aaaa") -> Iyar/Tuesday | C6: Supermercados Nori | D6: FERMENTADO ITAMBE | E6: Laticinios | F6: 1 | G6: UN | H6: 14.5 | I6: =IFERROR(H6/F6,0) -> 14.5 | J6: Cupom 00091475
A7: 46147 | B7: =TEXT(A7,"mmm/aaaa") -> Iyar/Tuesday | C7: Supermercados Nori | D7: REQUEIJAO VIGOR | E7: Laticinios | F7: 1 | G7: UN | H7: 17.5 | I7: =IFERROR(H7/F7,0) -> 17.5 | J7: Cupom 00091475
A8: 46147 | B8: =TEXT(A8,"mmm/aaaa") -> Iyar/Tuesday | C8: Supermercados Nori | D8: MARGARINA DELICIA | E8: Laticinios | F8: 1 | G8: UN | H8: 6.25 | I8: =IFERROR(H8/F8,0) -> 6.25 | J8: Cupom 00091475
A9: 46147 | B9: =TEXT(A9,"mmm/aaaa") -> Iyar/Tuesday | C9: Supermercados Nori | D9: LEITE SERRALAT PADRAO | E9: Laticinios | F9: 1 | G9: UN | H9: 6.65 | I9: =IFERROR(H9/F9,0) -> 6.65 | J9: Cupom 00091475
A10: 46147 | B10: =TEXT(A10,"mmm/aaaa") -> Iyar/Tuesday | C10: Supermercados Nori | D10: CAFE 3 CORACOES | E10: Mercearia | F10: 1 | G10: UN | H10: 23 | I10: =IFERROR(H10/F10,0) -> 23 | J10: Cupom 00091475
A11: 46147 | B11: =TEXT(A11,"mmm/aaaa") -> Iyar/Tuesday | C11: Supermercados Nori | D11: AMENDOIM DELTA | E11: Mercearia | F11: 1 | G11: UN | H11: 10.99 | I11: =IFERROR(H11/F11,0) -> 10.99 | J11: Cupom 00091475
A12: 46147 | B12: =TEXT(A12,"mmm/aaaa") -> Iyar/Tuesday | C12: Supermercados Nori | D12: ACUCAR CRISTAL | E12: Mercearia | F12: 1 | G12: UN | H12: 5.75 | I12: =IFERROR(H12/F12,0) -> 5.75 | J12: Cupom 00091475
A13: 46147 | B13: =TEXT(A13,"mmm/aaaa") -> Iyar/Tuesday | C13: Supermercados Nori | D13: SAL LEBRE MARINHO | E13: Mercearia | F13: 1 | G13: UN | H13: 2.49 | I13: =IFERROR(H13/F13,0) -> 2.49 | J13: Cupom 00091475
A14: 46147 | B14: =TEXT(A14,"mmm/aaaa") -> Iyar/Tuesday | C14: Supermercados Nori | D14: BISCOITO TUCS | E14: Mercearia | F14: 3 | G14: UN | H14: 5.4 | I14: =IFERROR(H14/F14,0) -> 1.8 | J14: Cupom 00091475
A15: 46147 | B15: =TEXT(A15,"mmm/aaaa") -> Iyar/Tuesday | C15: Supermercados Nori | D15: BISCOITO NESFIT | E15: Mercearia | F15: 1 | G15: UN | H15: 3.7 | I15: =IFERROR(H15/F15,0) -> 3.7 | J15: Cupom 00091475
A16: 46147 | B16: =TEXT(A16,"mmm/aaaa") -> Iyar/Tuesday | C16: Supermercados Nori | D16: BISCOITO NESFIT | E16: Mercearia | F16: 3 | G16: UN | H16: 11.1 | I16: =IFERROR(H16/F16,0) -> 3.7 | J16: Cupom 00091475
... A37: 46147 | B37: =TEXT(A37,"mmm/aaaa") -> Iyar/Tuesday | C37: Supermercados Nori | D37: SABAO PO SURF | E37: Limpeza | F37: 1 | G37: UN | H37: 16.6 | I37: =IFERROR(H37/F37,0) -> 16.6 | J37: Cupom 00091475
A38: 46148 | B38: =TEXT(A38,"mmm/aaaa") -> Iyar/Wednesday | C38: Varejao Monteverde | D38: BERINJELA | E38: Hortifruti | F38: 0.574 | G38: KG | H38: 2 | I38: =IFERROR(H38/F38,0) -> 3.4843206 | J38: NFC-e Varejao Monteverde 2410 | K38: Item da nota do Varejao Monteverde
A39: 46148 | B39: =TEXT(A39,"mmm/aaaa") -> Iyar/Wednesday | C39: Varejao Monteverde | D39: BANANA NANICA | E39: Hortifruti | F39: 1.504 | G39: KG | H39: 7.49 | I39: =IFERROR(H39/F39,0) -> 4.9800532 | J39: NFC-e Varejao Monteverde 2410 | K39: Item da nota do Varejao Monteverde
A40: 46148 | B40: =TEXT(A40,"mmm/aaaa") -> Iyar/Wednesday | C40: Varejao Monteverde | D40: MACA GALA | E40: Hortifruti | F40: 0.702 | G40: KG | H40: 8.2 | I40: =IFERROR(H40/F40,0) -> 11.680912 | J40: NFC-e Varejao Monteverde 2410 | K40: Item da nota do Varejao Monteverde
A41: 46144 | B41: =TEXT(A41,"mmm/aaaa") -> Iyar/Shabbat | C41: Crystal | D41: BISCOITO SIMPLES KG | E41: Padaria | F41: 0.085935132 | G41: KG | H41: 5.67 | I41: =IFERROR(H41/F41,0) -> 65.98 | J41: NFC-e Crystal 000052920 | K41: Quantidade calculada pelo total/preco unitario da nota: 5,67 / 65,98 = 0,0859 kg.
A42: 46144 | B42: =TEXT(A42,"mmm/aaaa") -> Iyar/Shabbat | C42: Crystal | D42: BOLACHA TRANCADINHA DE CANELA 250G | E42: Mercearia | F42: 1 | G42: UN | H42: 11.98 | I42: =IFERROR(H42/F42,0) -> 11.98 | J42: NFC-e Crystal 000052920 | K42: Item da nota Crystal
A43: 46144 | B43: =TEXT(A43,"mmm/aaaa") -> Iyar/Shabbat | C43: Crystal | D43: PAO FRANCES KG | E43: Padaria | F43: 0.59 | G43: KG | H43: 10.02 | I43: =IFERROR(H43/F43,0) -> 16.983051 | J43: NFC-e Crystal 000052920 | K43: Item da nota Crystal
A44: 46151 | B44: =TEXT(A44,"mmm/aaaa") -> Iyar/Shabbat | C44: Supermercado Canesin | D44: LIMAO KG | E44: Hortifruti | F44: 0.645 | G44: KG | H44: 1.28 | I44: =IFERROR(H44/F44,0) -> 1.9844961 | J44: NFC-e Canesin 000038274 | K44: Item da nota Canesin (Brodowski-SP)
A45: 46151 | B45: =TEXT(A45,"mmm/aaaa") -> Iyar/Shabbat | C45: Supermercado Canesin | D45: GRAO DE BICO KODILAR | E45: Mercearia | F45: 1 | G45: UN | H45: 14.9 | I45: =IFERROR(H45/F45,0) -> 14.9 | J45: NFC-e Canesin 000038274 | K45: Item da nota Canesin (Brodowski-SP)
A46: 46152 | B46: =TEXT(A46,"mmm/aaaa") -> Iyar/Sunday | C46: Casa de Carnes Barao da Carne | D46: COSTELINHA TEMP SUIN | E46: Carnes | F46: 1.04 | G46: KG | H46: 34.22 | I46: =IFERROR(H46/F46,0) -> 32.903846 | J46: Orcamento Pedido 083825 | K46: Casa de Carnes Barao da Carne (Brodowski-SP) - Sem Valor Fiscal
A47: 46152 | B47: =TEXT(A47,"mmm/aaaa") -> Iyar/Sunday | C47: Casa de Carnes Barao da Carne | D47: PERNIL CARNEIRO TEMP | E47: Carnes | F47: 0.554 | G47: KG | H47: 44.26 | I47: =IFERROR(H47/F47,0) -> 79.891697 | J47: Orcamento Pedido 083825 | K47: Casa de Carnes Barao da Carne (Brodowski-SP) - Sem Valor Fiscal
A48: 46152 | B48: =TEXT(A48,"mmm/aaaa") -> Iyar/Sunday | C48: Varejao Monteverde | D48: BANANA NANICA | E48: Hortifruti | F48: 1.312 | G48: KG | H48: 6.53 | I48: =IFERROR(H48/F48,0) -> 4.9771341 | J48: NFC-e Varejao Monteverde 8933 | K48: Item da nota do Varejao Monteverde - 10/05/2026
A49: 46152 | B49: =TEXT(A49,"mmm/aaaa") -> Iyar/Sunday | C49: Varejao Monteverde | D49: OVOS SEMI CAIPIRA | E49: Mercearia | F49: 6 | G49: UN | H49: 7.2 | I49: =IFERROR(H49/F49,0) -> 1.2 | J49: NFC-e Varejao Monteverde 8933 | K49: Item da nota do Varejao Monteverde - 10/05/2026
... A63: 46158 | B63: =TEXT(A63,"mmm/aaaa") -> Iyar/Shabbat | C63: Varejao Nova Brasil | D63: Limão Taiti | E63: Hortifruti | F63: 0.635 | G63: KG | H63: 5.07 | I63: =IFERROR(H63/F63,0) -> 7.984252 | J63: Cupom Não Fiscal | K63: R$ 7,99/kg
A64: 46157 | B64: =TEXT(A64,"mmm/aaaa") -> Iyar/Friday | C64: Supermercados Nori | D64: Fubá Zei | E64: Mercearia | F64: 1 | G64: UN | H64: 3.6 | I64: =IFERROR(H64/F64,0) -> 3.6 | J64: NFC-e 65290
A65: 46157 | B65: =TEXT(A65,"mmm/aaaa") -> Iyar/Friday | C65: Supermercados Nori | D65: Feijão Preto Empório | E65: Mercearia | F65: 1 | G65: UN | H65: 7.99 | I65: =IFERROR(H65/F65,0) -> 7.99 | J65: NFC-e 65290
A66: 46157 | B66: =TEXT(A66,"mmm/aaaa") -> Iyar/Friday | C66: Supermercados Nori | D66: Café TM Padrão | E66: Mercearia | F66: 1 | G66: UN | H66: 21 | I66: =IFERROR(H66/F66,0) -> 21 | J66: NFC-e 65290
A67: 46157 | B67: =TEXT(A67,"mmm/aaaa") -> Iyar/Friday | C67: Supermercados Nori | D67: Lentilha Kinino | E67: Mercearia | F67: 1 | G67: UN | H67: 10.7 | I67: =IFERROR(H67/F67,0) -> 10.7 | J67: NFC-e 65290
A68: 46157 | B68: =TEXT(A68,"mmm/aaaa") -> Iyar/Friday | C68: Supermercados Nori | D68: Milho Pipoca Kinino | E68: Mercearia | F68: 1 | G68: UN | H68: 3.89 | I68: =IFERROR(H68/F68,0) -> 3.89 | J68: NFC-e 65290
A69: 46157 | B69: =TEXT(A69,"mmm/aaaa") -> Iyar/Friday | C69: Supermercados Nori | D69: Salgadinhos Balatore | E69: Mercearia | F69: 1 | G69: UN | H69: 9.2 | I69: =IFERROR(H69/F69,0) -> 9.2 | J69: NFC-e 65290
A70: 46157 | B70: =TEXT(A70,"mmm/aaaa") -> Iyar/Friday | C70: Supermercados Nori | D70: Grão de Bico | E70: Mercearia | F70: 1 | G70: UN | H70: 11.99 | I70: =IFERROR(H70/F70,0) -> 11.99 | J70: NFC-e 65290
A71: 46157 | B71: =TEXT(A71,"mmm/aaaa") -> Iyar/Friday | C71: Supermercados Nori | D71: Macarrão Galo | E71: Mercearia | F71: 1 | G71: UN | H71: 2.95 | I71: =IFERROR(H71/F71,0) -> 2.95 | J71: NFC-e 65290
A72: 46157 | B72: =TEXT(A72,"mmm/aaaa") -> Iyar/Friday | C72: Supermercados Nori | D72: Chá Condinew Hibisco | E72: Mercearia | F72: 1 | G72: UN | H72: 2.75 | I72: =IFERROR(H72/F72,0) -> 2.75 | J72: NFC-e 65290
A73: 46157 | B73: =TEXT(A73,"mmm/aaaa") -> Iyar/Friday | C73: Supermercados Nori | D73: Erva Doce Condinew | E73: Mercearia | F73: 1 | G73: UN | H73: 3.85 | I73: =IFERROR(H73/F73,0) -> 3.85 | J73: NFC-e 65290
A74: 46157 | B74: =TEXT(A74,"mmm/aaaa") -> Iyar/Friday | C74: Supermercados Nori | D74: Lemon Pepper | E74: Mercearia | F74: 1 | G74: UN | H74: 3.85 | I74: =IFERROR(H74/F74,0) -> 3.85 | J74: NFC-e 65290
A75: 46157 | B75: =TEXT(A75,"mmm/aaaa") -> Iyar/Friday | C75: Supermercados Nori | D75: Cravo da Índia | E75: Mercearia | F75: 1 | G75: UN | H75: 3.5 | I75: =IFERROR(H75/F75,0) -> 3.5 | J75: NFC-e 65290
... A77: 46157 | B77: =TEXT(A77,"mmm/aaaa") -> Iyar/Friday | C77: Supermercados Nori | D77: Creme Dental Oral-B | E77: Higiene | F77: 1 | G77: UN | H77: 2.35 | I77: =IFERROR(H77/F77,0) -> 2.35 | J77: NFC-e 65290
A78: 46157 | B78: =TEXT(A78,"mmm/aaaa") -> Iyar/Friday | C78: Supermercados Nori | D78: Queijo Parmesão | E78: Laticínios | F78: 0.112 | G78: KG | H78: 12.32 | I78: =IFERROR(H78/F78,0) -> 110 | J78: NFC-e 65290 | K78: R$ 110,00/kg
A79: 46157 | B79: =TEXT(A79,"mmm/aaaa") -> Iyar/Friday | C79: Supermercados Nori | D79: Azeitona Verde | E79: Mercearia | F79: 1 | G79: UN | H79: 6.35 | I79: =IFERROR(H79/F79,0) -> 6.35 | J79: NFC-e 65290
A80: 46157 | B80: =TEXT(A80,"mmm/aaaa") -> Iyar/Friday | C80: Supermercados Nori | D80: Biscoito Tucs | E80: Mercearia | F80: 2 | G80: UN | H80: 3.6 | I80: =IFERROR(H80/F80,0) -> 1.8 | J80: NFC-e 65290 | K80: R$ 1,80/un
A81: 46157 | B81: =TEXT(A81,"mmm/aaaa") -> Iyar/Friday | C81: Supermercados Nori | D81: Biscoito Tucs | E81: Mercearia | F81: 2 | G81: UN | H81: 3.6 | I81: =IFERROR(H81/F81,0) -> 1.8 | J81: NFC-e 65290 | K81: R$ 1,80/un - 2º código
A82: 46157 | B82: =TEXT(A82,"mmm/aaaa") -> Iyar/Friday | C82: Supermercados Nori | D82: Biscoito Nesfit | E82: Mercearia | F82: 3 | G82: UN | H82: 11.1 | I82: =IFERROR(H82/F82,0) -> 3.7 | J82: NFC-e 65290 | K82: R$ 3,70/un
A83: 46157 | B83: =TEXT(A83,"mmm/aaaa") -> Iyar/Friday | C83: Supermercados Nori | D83: Biscoito Nesfit | E83: Mercearia | F83: 1 | G83: UN | H83: 3.7 | I83: =IFERROR(H83/F83,0) -> 3.7 | J83: NFC-e 65290
A84: 46157 | B84: =TEXT(A84,"mmm/aaaa") -> Iyar/Friday | C84: Supermercados Nori | D84: Farinha de Trigo | E84: Mercearia | F84: 1 | G84: UN | H84: 4.6 | I84: =IFERROR(H84/F84,0) -> 4.6 | J84: NFC-e 65290
A85: 46157 | B85: =TEXT(A85,"mmm/aaaa") -> Iyar/Friday | C85: Supermercados Nori | D85: Extrato Tomate Predilecta | E85: Mercearia | F85: 1 | G85: UN | H85: 5.45 | I85: =IFERROR(H85/F85,0) -> 5.45 | J85: NFC-e 65290
A86: 46157 | B86: =TEXT(A86,"mmm/aaaa") -> Iyar/Friday | C86: Supermercados Nori | D86: Amendoim Vó Délia | E86: Mercearia | F86: 1 | G86: UN | H86: 11.2 | I86: =IFERROR(H86/F86,0) -> 11.2 | J86: NFC-e 65290
A87: 46157 | B87: =TEXT(A87,"mmm/aaaa") -> Iyar/Friday | C87: Supermercados Nori | D87: Arroz Broto Legal | E87: Mercearia | F87: 1 | G87: UN | H87: 6.2 | I87: =IFERROR(H87/F87,0) -> 6.2 | J87: NFC-e 65290
A88: 46157 | B88: =TEXT(A88,"mmm/aaaa") -> Iyar/Friday | C88: Supermercados Nori | D88: Arroz Rio do Sol | E88: Mercearia | F88: 1 | G88: UN | H88: 7.7 | I88: =IFERROR(H88/F88,0) -> 7.7 | J88: NFC-e 65290
A89: 46157 | B89: =TEXT(A89,"mmm/aaaa") -> Iyar/Friday | C89: Supermercados Nori | D89: Esponja de Aço | E89: Limpeza | F89: 1 | G89: UN | H89: 3.85 | I89: =IFERROR(H89/F89,0) -> 3.85 | J89: NFC-e 65290
A90: 46157 | B90: =TEXT(A90,"mmm/aaaa") -> Iyar/Friday | C90: Supermercados Nori | D90: Creme de Leite Italac | E90: Laticínios | F90: 3 | G90: UN | H90: 7.47 | I90: =IFERROR(H90/F90,0) -> 2.49 | J90: NFC-e 65290 | K90: R$ 2,49/un
A91: 46157 | B91: =TEXT(A91,"mmm/aaaa") -> Iyar/Friday | C91: Supermercados Nori | D91: Milho Verde | E91: Mercearia | F91: 2 | G91: UN | H91: 6.2 | I91: =IFERROR(H91/F91,0) -> 3.1 | J91: NFC-e 65290 | K91: R$ 3,10/un
A92: 46157 | B92: =TEXT(A92,"mmm/aaaa") -> Iyar/Friday | C92: Supermercados Nori | D92: Seleta de Legumes | E92: Mercearia | F92: 1 | G92: UN | H92: 3.49 | I92: =IFERROR(H92/F92,0) -> 3.49 | J92: NFC-e 65290
A93: 46157 | B93: =TEXT(A93,"mmm/aaaa") -> Iyar/Friday | C93: Supermercados Nori | D93: Ervilha Predilecta | E93: Mercearia | F93: 1 | G93: UN | H93: 3.05 | I93: =IFERROR(H93/F93,0) -> 3.05 | J93: NFC-e 65290
A94: 46157 | B94: =TEXT(A94,"mmm/aaaa") -> Iyar/Friday | C94: Supermercados Nori | D94: Pão Visconti Forma | E94: Padaria | F94: 1 | G94: UN | H94: 7.2 | I94: =IFERROR(H94/F94,0) -> 7.2 | J94: NFC-e 65290
A95: 46157 | B95: =TEXT(A95,"mmm/aaaa") -> Iyar/Friday | C95: Supermercados Nori | D95: Pão Visconti | E95: Padaria | F95: 1 | G95: UN | H95: 5.7 | I95: =IFERROR(H95/F95,0) -> 5.7 | J95: NFC-e 65290
A96: 46157 | B96: =TEXT(A96,"mmm/aaaa") -> Iyar/Friday | C96: Supermercados Nori | D96: Rosquinha Goiabada | E96: Padaria | F96: 0.132 | G96: KG | H96: 5.15 | I96: =IFERROR(H96/F96,0) -> 39.015152 | J96: NFC-e 65290 | K96: R$ 39,00/kg
A97: 46157 | B97: =TEXT(A97,"mmm/aaaa") -> Iyar/Friday | C97: Supermercados Nori | D97: Pãezinhos de Batata | E97: Padaria | F97: 0.244 | G97: KG | H97: 7.81 | I97: =IFERROR(H97/F97,0) -> 32.008197 | J97: NFC-e 65290 | K97: R$ 32,00/kg
A98: 46157 | B98: =TEXT(A98,"mmm/aaaa") -> Iyar/Friday | C98: Supermercados Nori | D98: Pão Francês (Filão) | E98: Padaria | F98: 0.536 | G98: KG | H98: 7.99 | I98: =IFERROR(H98/F98,0) -> 14.906716 | J98: NFC-e 65290 | K98: R$ 14,90/kg
A99: 46157 | B99: =TEXT(A99,"mmm/aaaa") -> Iyar/Friday | C99: Supermercados Nori | D99: Aveia Nestlé Flocos | E99: Mercearia | F99: 1 | G99: UN | H99: 10.2 | I99: =IFERROR(H99/F99,0) -> 10.2 | J99: NFC-e 65290
A100: 46157 | B100: =TEXT(A100,"mmm/aaaa") -> Iyar/Friday | C100: Supermercados Nori | D100: Aveia Nestlé | E100: Mercearia | F100: 1 | G100: UN | H100: 10.2 | I100: =IFERROR(H100/F100,0) -> 10.2 | J100: NFC-e 65290
A101: 46157 | B101: =TEXT(A101,"mmm/aaaa") -> Iyar/Friday | C101: Supermercados Nori | D101: Ketchup | E101: Mercearia | F101: 1 | G101: UN | H101: 11.9 | I101: =IFERROR(H101/F101,0) -> 11.9 | J101: NFC-e 65290
A102: 46157 | B102: =TEXT(A102,"mmm/aaaa") -> Iyar/Friday | C102: Supermercados Nori | D102: Leite de Coco Menina | E102: Mercearia | F102: 1 | G102: UN | H102: 4.45 | I102: =IFERROR(H102/F102,0) -> 4.45 | J102: NFC-e 65290
A103: 46157 | B103: =TEXT(A103,"mmm/aaaa") -> Iyar/Friday | C103: Supermercados Nori | D103: Suco de Uva Garibaldi | E103: Bebidas | F103: 1 | G103: UN | H103: 16.4 | I103: =IFERROR(H103/F103,0) -> 16.4 | J103: NFC-e 65290
A104: 46157 | B104: =TEXT(A104,"mmm/aaaa") -> Iyar/Friday | C104: Supermercados Nori | D104: Limpa Pisos Rajjalim | E104: Limpeza | F104: 1 | G104: UN | H104: 6.49 | I104: =IFERROR(H104/F104,0) -> 6.49 | J104: NFC-e 65290
A105: 46157 | B105: =TEXT(A105,"mmm/aaaa") -> Iyar/Friday | C105: Supermercados Nori | D105: Água Sanitária Triex | E105: Limpeza | F105: 1 | G105: UN | H105: 4.8 | I105: =IFERROR(H105/F105,0) -> 4.8 | J105: NFC-e 65290
A106: 46157 | B106: =TEXT(A106,"mmm/aaaa") -> Iyar/Friday | C106: Supermercados Nori | D106: Sabonete Plush Flores | E106: Higiene | F106: 1 | G106: UN | H106: 5.7 | I106: =IFERROR(H106/F106,0) -> 5.7 | J106: NFC-e 65290
A107: 46157 | B107: =TEXT(A107,"mmm/aaaa") -> Iyar/Friday | C107: Supermercados Nori | D107: Sabão Pasta Alumil | E107: Limpeza | F107: 1 | G107: UN | H107: 9.7 | I107: =IFERROR(H107/F107,0) -> 9.7 | J107: NFC-e 65290
A108: 46157 | B108: =TEXT(A108,"mmm/aaaa") -> Iyar/Friday | C108: Supermercados Nori | D108: Detergente Triex | E108: Limpeza | F108: 1 | G108: UN | H108: 1.99 | I108: =IFERROR(H108/F108,0) -> 1.99 | J108: NFC-e 65290
A109: 46157 | B109: =TEXT(A109,"mmm/aaaa") -> Iyar/Friday | C109: Supermercados Nori | D109: Toalha de Papel | E109: Limpeza | F109: 1 | G109: UN | H109: 3.9 | I109: =IFERROR(H109/F109,0) -> 3.9 | J109: NFC-e 65290
A110: 46157 | B110: =TEXT(A110,"mmm/aaaa") -> Iyar/Friday | C110: Supermercados Nori | D110: Papel Higiênico Qualité | E110: Higiene | F110: 1 | G110: UN | H110: 13.95 | I110: =IFERROR(H110/F110,0) -> 13.95 | J110: NFC-e 65290
... A114: 46156 | B114: =TEXT(A114,"mmm/aaaa") -> Iyar/Thursday | C114: Varejao Monteverde | D114: Brócolis Japonês | E114: Hortifruti | F114: 1 | G114: UN | H114: 9.9 | I114: =IFERROR(H114/F114,0) -> 9.9 | J114: NFC-e 3067
A115: 46156 | B115: =TEXT(A115,"mmm/aaaa") -> Iyar/Thursday | C115: Varejao Monteverde | D115: Alho a Granel | E115: Hortifruti | F115: 0.136 | G115: KG | H115: 3.53 | I115: =IFERROR(H115/F115,0) -> 25.955882 | J115: NFC-e 3067 | K115: R$ 25,98/kg
A116: 46156 | B116: =TEXT(A116,"mmm/aaaa") -> Iyar/Thursday | C116: Varejao Monteverde | D116: Cebola Roxa | E116: Hortifruti | F116: 0.362 | G116: KG | H116: 3 | I116: =IFERROR(H116/F116,0) -> 8.2872928 | J116: NFC-e 3067 | K116: R$ 8,28/kg
A117: 46156 | B117: =TEXT(A117,"mmm/aaaa") -> Iyar/Thursday | C117: Varejao Monteverde | D117: Ovos Semi Caipira | E117: Mercearia | F117: 12 | G117: UN | H117: 14.4 | I117: =IFERROR(H117/F117,0) -> 1.2 | J117: NFC-e 3067 | K117: R$ 1,20/un (dúzia)
A118: 46156 | B118: =TEXT(A118,"mmm/aaaa") -> Iyar/Thursday | C118: Andre Novato Ribeiro | D118: Pão de Forma Pullman | E118: Padaria | F118: 1 | G118: UN | H118: 9.99 | I118: =IFERROR(H118/F118,0) -> 9.99 | J118: Nota 36741
A119: 46156 | B119: =TEXT(A119,"mmm/aaaa") -> Iyar/Thursday | C119: Andre Novato Ribeiro | D119: Café Padrão 500g | E119: Mercearia | F119: 1 | G119: UN | H119: 29.99 | I119: =IFERROR(H119/F119,0) -> 29.99 | J119: Nota 36741
A120: 46159 | B120: =TEXT(A120,"mmm/aaaa") -> Sivan/Sunday | C120: Supermercados Nori | D120: AGUA MINERAL CRISTAL | E120: Bebidas | F120: 4 | G120: UN | H120: 5.96 | I120: 1.49 | J120: NFC-e 22022 Cupom 00071051 | K120: Supermercados Nori (Av. Rebouças, 70 - Brodowski/SP)
A121: 46159 | B121: =TEXT(A121,"mmm/aaaa") -> Sivan/Sunday | C121: Supermercados Nori | D121: PAO FRANCES (FILAO) | E121: Padaria | F121: 0.398 | G121: KG | H121: 5.93 | I121: 14.9 | J121: NFC-e 22022 Cupom 00071051 | K121: R$ 14,90/kg
A122: 46159 | B122: =TEXT(A122,"mmm/aaaa") -> Sivan/Sunday | C122: Supermercados Nori | D122: BATATA RUFFLES | E122: Mercearia | F122: 1 | G122: UN | H122: 15.9 | I122: 15.9 | J122: NFC-e 22022 Cupom 00071051
A123: 46159 | B123: =TEXT(A123,"mmm/aaaa") -> Sivan/Sunday | C123: Supermercados Nori | D123: BOMBOM AMOR CARIOCA | E123: Mercearia | F123: 1 | G123: UN | H123: 11.6 | I123: 11.6 | J123: NFC-e 22022 Cupom 00071051
A124: 46159 | B124: =TEXT(A124,"mmm/aaaa") -> Sivan/Sunday | C124: Supermercados Nori | D124: BATATA PRINGLES | E124: Mercearia | F124: 1 | G124: UN | H124: 11.99 | I124: 11.99 | J124: NFC-e 22022 Cupom 00071051
A125: 46159 | B125: =TEXT(A125,"mmm/aaaa") -> Sivan/Sunday | C125: Supermercados Nori | D125: LEITE FERMENTADO | E125: Laticinios | F125: 2 | G125: UN | H125: 16.5 | I125: 8.25 | J125: NFC-e 22022 Cupom 00071051 | K125: R$ 8,25/un
A126: 46159 | B126: =TEXT(A126,"mmm/aaaa") -> Sivan/Sunday | C126: Supermercados Nori | D126: ROSCA DE ACUCAR | E126: Padaria | F126: 0.388 | G126: KG | H126: 11.25 | I126: 29 | J126: NFC-e 22022 Cupom 00071051 | K126: R$ 29,00/kg
A127: 46159 | B127: =TEXT(A127,"mmm/aaaa") -> Sivan/Sunday | C127: Supermercados Nori | D127: PRESUNTO PERDIGAO | E127: Frios | F127: 0.314 | G127: KG | H127: 8.13 | I127: 25.9 | J127: NFC-e 22022 Cupom 00071051 | K127: R$ 25,90/kg
A128: 46159 | B128: =TEXT(A128,"mmm/aaaa") -> Sivan/Sunday | C128: Supermercados Nori | D128: QJO MUSSARELA DAVACA | E128: Frios | F128: 0.316 | G128: KG | H128: 15.48 | I128: 49 | J128: NFC-e 22022 Cupom 00071051 | K128: R$ 49,00/kg
A129: 46161 | B129: =TEXT(A129,"mmm/aaaa") -> Sivan/Tuesday | C129: Supermercado Canesin | D129: Gatorade 350ml | E129: Bebidas | F129: 2 | G129: UN | H129: 9.98 | I129: =IFERROR(H129/F129,0) -> 4.99 | J129: NFC-e 50028 | K129: Cartão de crédito
A130: 46161 | B130: =TEXT(A130,"mmm/aaaa") -> Sivan/Tuesday | C130: Supermercado Canesin | D130: Pão Francês (filão) | E130: Padaria | F130: 0.395 | G130: KG | H130: 7.07 | I130: =IFERROR(H130/F130,0) -> 17.898734 | J130: NFC-e 50028 | K130: Cartão de crédito
A131: 46162 | B131: =TEXT(A131,"mmm/aaaa") -> Sivan/Wednesday | C131: Andre Eduardo Hipolito | D131: Pão Francês | E131: Padaria | F131: 0.45 | G131: KG | H131: 6.75 | I131: =IFERROR(H131/F131,0) -> 15 | J131: Cupom não fiscal DOC 038073 | K131: Cartão de crédito
A132: 46162 | B132: =TEXT(A132,"mmm/aaaa") -> Sivan/Wednesday | C132: Andre Eduardo Hipolito | D132: Pão de Queijo | E132: Padaria | F132: 0.235 | G132: KG | H132: 9.64 | I132: =IFERROR(H132/F132,0) -> 41.021277 | J132: Cupom não fiscal DOC 038073 | K132: Cartão de crédito
A133: 46162 | B133: =TEXT(A133,"mmm/aaaa") -> Sivan/Wednesday | C133: Andre Eduardo Hipolito | D133: Power Mix Frutas 500ml | E133: Bebidas | F133: 2 | G133: UN | H133: 12.8 | I133: =IFERROR(H133/F133,0) -> 6.4 | J133: Cupom não fiscal DOC 038073 | K133: Cartão de crédito
A134: 46162 | B134: =TEXT(A134,"mmm/aaaa") -> Sivan/Wednesday | C134: Andre Eduardo Hipolito | D134: Biscoito Simples | E134: Padaria | F134: 0.166 | G134: KG | H134: 6.81 | I134: =IFERROR(H134/F134,0) -> 41.024096 | J134: Cupom não fiscal DOC 038073 | K134: Cartão de crédito
A135: 46163 | B135: =TEXT(A135,"mmm/aaaa") -> Sivan/Thursday | C135: Varejao Monteverde | D135: LARANJA PERA | E135: Hortifruti | F135: 1.266 | G135: KG | H135: 5.04 | I135: =IFERROR(H135/F135,0) -> 3.9810427 | J135: NFC-e 3243 Série 3 | K135: Cartão de crédito
A136: 46163 | B136: =TEXT(A136,"mmm/aaaa") -> Sivan/Thursday | C136: Varejao Monteverde | D136: ALHO PORO | E136: Hortifruti | F136: 1 | G136: UN | H136: 3.9 | I136: =IFERROR(H136/F136,0) -> 3.9 | J136: NFC-e 3243 Série 3 | K136: Cartão de crédito
A137: 46163 | B137: =TEXT(A137,"mmm/aaaa") -> Sivan/Thursday | C137: Varejao Monteverde | D137: CENOURA | E137: Hortifruti | F137: 0.786 | G137: KG | H137: 8.87 | I137: =IFERROR(H137/F137,0) -> 11.284987 | J137: NFC-e 3243 Série 3 | K137: Cartão de crédito
A138: 46163 | B138: =TEXT(A138,"mmm/aaaa") -> Sivan/Thursday | C138: Varejao Monteverde | D138: BATATA EXTRA | E138: Hortifruti | F138: 1.256 | G138: KG | H138: 13.79 | I138: =IFERROR(H138/F138,0) -> 10.979299 | J138: NFC-e 3243 Série 3 | K138: Cartão de crédito
...

Sheet Comparador
Q1: Todas
B2: COMPARADOR DE PREÇOS | Q2: Açougue
B3: Onde cada produto já saiu mais barato e mais caro — e quanto dá para economizar comprando no lugar certo. Tudo em fórmula: atualiza sozinho pela aba Compras. | Q3: Bebidas
Q4: Café
B5: CATEGORIA (filtro ▾) | C5: PRODUTOS COMPARADOS | F5: ECONOMIA POSSÍVEL | H5: PRODUTOS C/ ECONOMIA | J5: PREÇO MÍNIMO MÉDIO | Q5: Carnes
B6: Todas | C6: =IF($B$6="Todas",COUNTA($B$25:$B$218),COUNTIF($D$25:$D$218,$B$6)) -> 194 | F6: =IF($B$6="Todas",SUM($K$25:$K$218),SUMIF($D$25:$D$218,$B$6,$K$25:$K$218)) -> 92.625378 | H6: =IF($B$6="Todas",COUNTIFS($K$25:$K$218,">0"),COUNTIFS($D$25:$D$218,$B$6,$K$25:$K$218,">0")) -> 57 | J6: =IFERROR(IF($B$6="Todas",AVERAGE($E$25:$E$218),AVERAGEIF($D$25:$D$218,$B$6,$E$25:$E$218)),0) -> 12.431325 | Q6: Frios
Q7: Frutas
B8: TOP 10 OPORTUNIDADES DE ECONOMIA | Q8: Higiene
B9: Maiores diferenças por unidade entre o preço mais caro e o mais barato já pagos — comece a economizar por aqui. A lista muda conforme a categoria escolhida acima. | Q9: Hortifruti
B10: Produto | C10: Categoria | E10: Menor R$ | F10: Onde + quando (mais barato) | H10: Última R$ | I10: Economia / un. | Q10: Laticinios
B11: =IFERROR(INDEX($B$25:$B$218,MATCH(LARGE($P$25:$P$218,1),$P$25:$P$218,0)),"") -> CAFE TM 3 CORACOES | C11: =IFERROR(INDEX($D$25:$D$218,MATCH(LARGE($P$25:$P$218,1),$P$25:$P$218,0)),"") -> Mercearia | E11: =IFERROR(INDEX($E$25:$E$218,MATCH(LARGE($P$25:$P$218,1),$P$25:$P$218,0)),"") -> 23 | F11: =IFERROR(INDEX($F$25:$F$218,MATCH(LARGE($P$25:$P$218,1),$P$25:$P$218,0))&" · "&TEXT(DAY(INDEX($G$25:$G$218,MATCH(LARGE($P$25:$P$218,1),$P$25:$P$218,0))),"00")&"/"&TEXT(MONTH(INDEX($G$25:$G$218,MATCH(LARGE($P$25:$P$218,1),$P$25:$P$218,0))),"00")&"/"&TEXT(MOD(YEAR(INDEX($G$25:$G$218,MATCH(LARGE($P$25:$P$218,1),$P$25:$P$218,0))),100),"00"),"") -> Supermercados Nori · 20/06/26 | H11: =IFERROR(INDEX($M$25:$M$218,MATCH(LARGE($P$25:$P$218,1),$P$25:$P$218,0)),"") -> 23 | I11: =IFERROR(INDEX($K$25:$K$218,MATCH(LARGE($P$25:$P$218,1),$P$25:$P$218,0)),"") -> 8.7 | Q11: Laticínios
B12: =IFERROR(INDEX($B$25:$B$218,MATCH(LARGE($P$25:$P$218,2),$P$25:$P$218,0)),"") -> Pão Francês | C12: =IFERROR(INDEX($D$25:$D$218,MATCH(LARGE($P$25:$P$218,2),$P$25:$P$218,0)),"") -> Padaria | E12: =IFERROR(INDEX($E$25:$E$218,MATCH(LARGE($P$25:$P$218,2),$P$25:$P$218,0)),"") -> 14.991597 | F12: =IFERROR(INDEX($F$25:$F$218,MATCH(LARGE($P$25:$P$218,2),$P$25:$P$218,0))&" · "&TEXT(DAY(INDEX($G$25:$G$218,MATCH(LARGE($P$25:$P$218,2),$P$25:$P$218,0))),"00")&"/"&TEXT(MONTH(INDEX($G$25:$G$218,MATCH(LARGE($P$25:$P$218,2),$P$25:$P$218,0))),"00")&"/"&TEXT(MOD(YEAR(INDEX($G$25:$G$218,MATCH(LARGE($P$25:$P$218,2),$P$25:$P$218,0))),100),"00"),"") -> André · 27/05/26 | H12: =IFERROR(INDEX($M$25:$M$218,MATCH(LARGE($P$25:$P$218,2),$P$25:$P$218,0)),"") -> 14.991597 | I12: =IFERROR(INDEX($K$25:$K$218,MATCH(LARGE($P$25:$P$218,2),$P$25:$P$218,0)),"") -> 7.9134313 | Q12: Limpeza
B13: =IFERROR(INDEX($B$25:$B$218,MATCH(LARGE($P$25:$P$218,3),$P$25:$P$218,0)),"") -> LIMAO KG | C13: =IFERROR(INDEX($D$25:$D$218,MATCH(LARGE($P$25:$P$218,3),$P$25:$P$218,0)),"") -> Hortifruti | E13: =IFERROR(INDEX($E$25:$E$218,MATCH(LARGE($P$25:$P$218,3),$P$25:$P$218,0)),"") -> 1.9844961 | F13: =IFERROR(INDEX($F$25:$F$218,MATCH(LARGE($P$25:$P$218,3),$P$25:$P$218,0))&" · "&TEXT(DAY(INDEX($G$25:$G$218,MATCH(LARGE($P$25:$P$218,3),$P$25:$P$218,0))),"00")&"/"&TEXT(MONTH(INDEX($G$25:$G$218,MATCH(LARGE($P$25:$P$218,3),$P$25:$P$218,0))),"00")&"/"&TEXT(MOD(YEAR(INDEX($G$25:$G$218,MATCH(LARGE($P$25:$P$218,3),$P$25:$P$218,0))),100),"00"),"") -> Supermercado Canesin · 09/05/26 | H13: =IFERROR(INDEX($M$25:$M$218,MATCH(LARGE($P$25:$P$218,3),$P$25:$P$218,0)),"") -> 9.8987342 | I13: =IFERROR(INDEX($K$25:$K$218,MATCH(LARGE($P$25:$P$218,3),$P$25:$P$218,0)),"") -> 7.9142381 | Q13: Mercearia
B14: =IFERROR(INDEX($B$25:$B$218,MATCH(LARGE($P$25:$P$218,4),$P$25:$P$218,0)),"") -> Ketchup | C14: =IFERROR(INDEX($D$25:$D$218,MATCH(LARGE($P$25:$P$218,4),$P$25:$P$218,0)),"") -> Mercearia | E14: =IFERROR(INDEX($E$25:$E$218,MATCH(LARGE($P$25:$P$218,4),$P$25:$P$218,0)),"") -> 5.9 | F14: =IFERROR(INDEX($F$25:$F$218,MATCH(LARGE($P$25:$P$218,4),$P$25:$P$218,0))&" · "&TEXT(DAY(INDEX($G$25:$G$218,MATCH(LARGE($P$25:$P$218,4),$P$25:$P$218,0))),"00")&"/"&TEXT(MONTH(INDEX($G$25:$G$218,MATCH(LARGE($P$25:$P$218,4),$P$25:$P$218,0))),"00")&"/"&TEXT(MOD(YEAR(INDEX($G$25:$G$218,MATCH(LARGE($P$25:$P$218,4),$P$25:$P$218,0))),100),"00"),"") -> Supermercados Nori · 31/05/26 | H14: =IFERROR(INDEX($M$25:$M$218,MATCH(LARGE($P$25:$P$218,4),$P$25:$P$218,0)),"") -> 5.9 | I14: =IFERROR(INDEX($K$25:$K$218,MATCH(LARGE($P$25:$P$218,4),$P$25:$P$218,0)),"") -> 6 | Q14: Padaria
B15: =IFERROR(INDEX($B$25:$B$218,MATCH(LARGE($P$25:$P$218,5),$P$25:$P$218,0)),"") -> KETCHUP | C15: =IFERROR(INDEX($D$25:$D$218,MATCH(LARGE($P$25:$P$218,5),$P$25:$P$218,0)),"") -> Mercearia | E15: =IFERROR(INDEX($E$25:$E$218,MATCH(LARGE($P$25:$P$218,5),$P$25:$P$218,0)),"") -> 5.9 | F15: =IFERROR(INDEX($F$25:$F$218,MATCH(LARGE($P$25:$P$218,5),$P$25:$P$218,0))&" · "&TEXT(DAY(INDEX($G$25:$G$218,MATCH(LARGE($P$25:$P$218,5),$P$25:$P$218,0))),"00")&"/"&TEXT(MONTH(INDEX($G$25:$G$218,MATCH(LARGE($P$25:$P$218,5),$P$25:$P$218,0))),"00")&"/"&TEXT(MOD(YEAR(INDEX($G$25:$G$218,MATCH(LARGE($P$25:$P$218,5),$P$25:$P$218,0))),100),"00"),"") -> Supermercados Nori · 31/05/26 | H15: =IFERROR(INDEX($M$25:$M$218,MATCH(LARGE($P$25:$P$218,5),$P$25:$P$218,0)),"") -> 5.9 | I15: =IFERROR(INDEX($K$25:$K$218,MATCH(LARGE($P$25:$P$218,5),$P$25:$P$218,0)),"") -> 6 | Q15: Pet
B16: =IFERROR(INDEX($B$25:$B$218,MATCH(LARGE($P$25:$P$218,6),$P$25:$P$218,0)),"") -> BATATA EXTRA | C16: =IFERROR(INDEX($D$25:$D$218,MATCH(LARGE($P$25:$P$218,6),$P$25:$P$218,0)),"") -> Hortifruti | E16: =IFERROR(INDEX($E$25:$E$218,MATCH(LARGE($P$25:$P$218,6),$P$25:$P$218,0)),"") -> 5.2827381 | F16: =IFERROR(INDEX($F$25:$F$218,MATCH(LARGE($P$25:$P$218,6),$P$25:$P$218,0))&" · "&TEXT(DAY(INDEX($G$25:$G$218,MATCH(LARGE($P$25:$P$218,6),$P$25:$P$218,0))),"00")&"/"&TEXT(MONTH(INDEX($G$25:$G$218,MATCH(LARGE($P$25:$P$218,6),$P$25:$P$218,0))),"00")&"/"&TEXT(MOD(YEAR(INDEX($G$25:$G$218,MATCH(LARGE($P$25:$P$218,6),$P$25:$P$218,0))),100),"00"),"") -> Varejao Monteverde · 17/07/26 | H16: =IFERROR(INDEX($M$25:$M$218,MATCH(LARGE($P$25:$P$218,6),$P$25:$P$218,0)),"") -> 5.2830189 | I16: =IFERROR(INDEX($K$25:$K$218,MATCH(LARGE($P$25:$P$218,6),$P$25:$P$218,0)),"") -> 5.6965613 | Q16: Rotisseria
B17: =IFERROR(INDEX($B$25:$B$218,MATCH(LARGE($P$25:$P$218,7),$P$25:$P$218,0)),"") -> Batata Palito | C17: =IFERROR(INDEX($D$25:$D$218,MATCH(LARGE($P$25:$P$218,7),$P$25:$P$218,0)),"") -> Mercearia | E17: =IFERROR(INDEX($E$25:$E$218,MATCH(LARGE($P$25:$P$218,7),$P$25:$P$218,0)),"") -> 15.79 | F17: =IFERROR(INDEX($F$25:$F$218,MATCH(LARGE($P$25:$P$218,7),$P$25:$P$218,0))&" · "&TEXT(DAY(INDEX($G$25:$G$218,MATCH(LARGE($P$25:$P$218,7),$P$25:$P$218,0))),"00")&"/"&TEXT(MONTH(INDEX($G$25:$G$218,MATCH(LARGE($P$25:$P$218,7),$P$25:$P$218,0))),"00")&"/"&TEXT(MOD(YEAR(INDEX($G$25:$G$218,MATCH(LARGE($P$25:$P$218,7),$P$25:$P$218,0))),100),"00"),"") -> Supermercados Nori · 20/06/26 | H17: =IFERROR(INDEX($M$25:$M$218,MATCH(LARGE($P$25:$P$218,7),$P$25:$P$218,0)),"") -> 15.79 | I17: =IFERROR(INDEX($K$25:$K$218,MATCH(LARGE($P$25:$P$218,7),$P$25:$P$218,0)),"") -> 5.21 | Q17: Saúde
B18: =IFERROR(INDEX($B$25:$B$218,MATCH(LARGE($P$25:$P$218,8),$P$25:$P$218,0)),"") -> LIMAO THAITI | C18: =IFERROR(INDEX($D$25:$D$218,MATCH(LARGE($P$25:$P$218,8),$P$25:$P$218,0)),"") -> Hortifruti | E18: =IFERROR(INDEX($E$25:$E$218,MATCH(LARGE($P$25:$P$218,8),$P$25:$P$218,0)),"") -> 2.6825843 | F18: =IFERROR(INDEX($F$25:$F$218,MATCH(LARGE($P$25:$P$218,8),$P$25:$P$218,0))&" · "&TEXT(DAY(INDEX($G$25:$G$218,MATCH(LARGE($P$25:$P$218,8),$P$25:$P$218,0))),"00")&"/"&TEXT(MONTH(INDEX($G$25:$G$218,MATCH(LARGE($P$25:$P$218,8),$P$25:$P$218,0))),"00")&"/"&TEXT(MOD(YEAR(INDEX($G$25:$G$218,MATCH(LARGE($P$25:$P$218,8),$P$25:$P$218,0))),100),"00"),"") -> Varejao Monteverde · 31/05/26 | H18: =IFERROR(INDEX($M$25:$M$218,MATCH(LARGE($P$25:$P$218,8),$P$25:$P$218,0)),"") -> 7.5051546 | I18: =IFERROR(INDEX($K$25:$K$218,MATCH(LARGE($P$25:$P$218,8),$P$25:$P$218,0)),"") -> 4.8225704
B19: =IFERROR(INDEX($B$25:$B$218,MATCH(LARGE($P$25:$P$218,9),$P$25:$P$218,0)),"") -> PAO FRANCES (FILAO) | C19: =IFERROR(INDEX($D$25:$D$218,MATCH(LARGE($P$25:$P$218,9),$P$25:$P$218,0)),"") -> Padaria | E19: =IFERROR(INDEX($E$25:$E$218,MATCH(LARGE($P$25:$P$218,9),$P$25:$P$218,0)),"") -> 14.891304 | F19: =IFERROR(INDEX($F$25:$F$218,MATCH(LARGE($P$25:$P$218,9),$P$25:$P$218,0))&" · "&TEXT(DAY(INDEX($G$25:$G$218,MATCH(LARGE($P$25:$P$218,9),$P$25:$P$218,0))),"00")&"/"&TEXT(MONTH(INDEX($G$25:$G$218,MATCH(LARGE($P$25:$P$218,9),$P$25:$P$218,0))),"00")&"/"&TEXT(MOD(YEAR(INDEX($G$25:$G$218,MATCH(LARGE($P$25:$P$218,9),$P$25:$P$218,0))),100),"00"),"") -> Supermercados Nori · 31/05/26 | H19: =IFERROR(INDEX($M$25:$M$218,MATCH(LARGE($P$25:$P$218,9),$P$25:$P$218,0)),"") -> 14.897959 | I19: =IFERROR(INDEX($K$25:$K$218,MATCH(LARGE($P$25:$P$218,9),$P$25:$P$218,0)),"") -> 3.0161031
B20: =IFERROR(INDEX($B$25:$B$218,MATCH(LARGE($P$25:$P$218,10),$P$25:$P$218,0)),"") -> BANANA NANICA | C20: =IFERROR(INDEX($D$25:$D$218,MATCH(LARGE($P$25:$P$218,10),$P$25:$P$218,0)),"") -> Hortifruti | E20: =IFERROR(INDEX($E$25:$E$218,MATCH(LARGE($P$25:$P$218,10),$P$25:$P$218,0)),"") -> 3.9827586 | F20: =IFERROR(INDEX($F$25:$F$218,MATCH(LARGE($P$25:$P$218,10),$P$25:$P$218,0))&" · "&TEXT(DAY(INDEX($G$25:$G$218,MATCH(LARGE($P$25:$P$218,10),$P$25:$P$218,0))),"00")&"/"&TEXT(MONTH(INDEX($G$25:$G$218,MATCH(LARGE($P$25:$P$218,10),$P$25:$P$218,0))),"00")&"/"&TEXT(MOD(YEAR(INDEX($G$25:$G$218,MATCH(LARGE($P$25:$P$218,10),$P$25:$P$218,0))),100),"00"),"") -> Supermercado Canesin · 04/06/26 | H20: =IFERROR(INDEX($M$25:$M$218,MATCH(LARGE($P$25:$P$218,10),$P$25:$P$218,0)),"") -> 6.9877883 | I20: =IFERROR(INDEX($K$25:$K$218,MATCH(LARGE($P$25:$P$218,10),$P$25:$P$218,0)),"") -> 3.0061148
B22: COMPARATIVO COMPLETO — PRODUTO A PRODUTO
B23: Menor e maior preço já pagos, onde foi, e a última compra. Barra azul = tamanho da economia possível. Última R$ verde = você pagou o mínimo · vermelho = pagou acima do mínimo.
B24: Produto | C24: Unid. | D24: Categoria | E24: Menor R$ | F24: Mercado (+ barato) | G24: Data | H24: Maior R$ | I24: Mercado (+ caro) | J24: Data | K24: Economia R$ | L24: Economia % | M24: Última R$ | N24: Última compra (onde · quando)
B25: Linguiça Fina | C25: KG | D25: Açougue | E25: =IFERROR(_xlfn.MINIFS(tblCompras[Preço Unit.],tblCompras[Produto],$B25,tblCompras[Unid.],$C25),"") -> 28.90625 | F25: =IFERROR(LOOKUP(2,1/((tblCompras[Produto]=$B25)*(tblCompras[Unid.]=$C25)*(tblCompras[Preço Unit.]=$E25)),tblCompras[Mercado]),"") -> Supermercados Nori | G25: =IFERROR(LOOKUP(2,1/((tblCompras[Produto]=$B25)*(tblCompras[Unid.]=$C25)*(tblCompras[Preço Unit.]=$E25)),tblCompras[Data]),"") -> 46146 | H25: =IFERROR(_xlfn.MAXIFS(tblCompras[Preço Unit.],tblCompras[Produto],$B25,tblCompras[Unid.],$C25),"") -> 28.90625 | I25: =IFERROR(LOOKUP(2,1/((tblCompras[Produto]=$B25)*(tblCompras[Unid.]=$C25)*(tblCompras[Preço Unit.]=$H25)),tblCompras[Mercado]),"") -> Supermercados Nori | J25: =IFERROR(LOOKUP(2,1/((tblCompras[Produto]=$B25)*(tblCompras[Unid.]=$C25)*(tblCompras[Preço Unit.]=$H25)),tblCompras[Data]),"") -> 46146 | K25: =IF(OR($E25="",$H25=""),"",MAX(0,$H25-$E25)) -> 0 | L25: =IF(OR($E25="",$H25="",$E25=0),"",($H25-$E25)/$E25) -> 0 | M25: =IFERROR(LOOKUP(2,1/((tblCompras[Produto]=$B25)*(tblCompras[Unid.]=$C25)*(tblCompras[Data]=_xlfn.MAXIFS(tblCompras[Data],tblCompras[Produto],$B25,tblCompras[Unid.],$C25))),tblCompras[Preço Unit.]),"") -> 28.90625 | N25: =IFERROR(LOOKUP(2,1/((tblCompras[Produto]=$B25)*(tblCompras[Unid.]=$C25)*(tblCompras[Data]=_xlfn.MAXIFS(tblCompras[Data],tblCompras[Produto],$B25,tblCompras[Unid.],$C25))),tblCompras[Mercado])&" · "&TEXT(DAY(_xlfn.MAXIFS(tblCompras[Data],tblCompras[Produto],$B25,tblCompras[Unid.],$C25)),"00")&"/"&TEXT(MONTH(_xlfn.MAXIFS(tblCompras[Data],tblCompras[Produto],$B25,tblCompras[Unid.],$C25)),"00")&"/"&TEXT(MOD(YEAR(_xlfn.MAXIFS(tblCompras[Data],tblCompras[Produto],$B25,tblCompras[Unid.],$C25)),100),"00"),"") -> Supermercados Nori · 04/05/26 | P25: =IF(AND(ISNUMBER($K25),$K25>0,OR($B$6="Todas",$D25=$B$6)),$K25+ROW()/100000,"")
B26: AGUA MINERAL CRISTAL | C26: UN | D26: Bebidas | E26: =IFERROR(_xlfn.MINIFS(tblCompras[Preço Unit.],tblCompras[Produto],$B26,tblCompras[Unid.],$C26),"") -> 1.29 | F26: =IFERROR(LOOKUP(2,1/((tblCompras[Produto]=$B26)*(tblCompras[Unid.]=$C26)*(tblCompras[Preço Unit.]=$E26)),tblCompras[Mercado]),"") -> Supermercados Nori | G26: =IFERROR(LOOKUP(2,1/((tblCompras[Produto]=$B26)*(tblCompras[Unid.]=$C26)*(tblCompras[Preço Unit.]=$E26)),tblCompras[Data]),"") -> 46243 | H26: =IFERROR(_xlfn.MAXIFS(tblCompras[Preço Unit.],tblCompras[Produto],$B26,tblCompras[Unid.],$C26),"") -> 1.65 | I26: =IFERROR(LOOKUP(2,1/((tblCompras[Produto]=$B26)*(tblCompras[Unid.]=$C26)*(tblCompras[Preço Unit.]=$H26)),tblCompras[Mercado]),"") -> Supermercados Nori | J26: =IFERROR(LOOKUP(2,1/((tblCompras[Produto]=$B26)*(tblCompras[Unid.]=$C26)*(tblCompras[Preço Unit.]=$H26)),tblCompras[Data]),"") -> 46215 | K26: =IF(OR($E26="",$H26=""),"",MAX(0,$H26-$E26)) -> 0.36 | L26: =IF(OR($E26="",$H26="",$E26=0),"",($H26-$E26)/$E26) -> 0.27906977 | M26: =IFERROR(LOOKUP(2,1/((tblCompras[Produto]=$B26)*(tblCompras[Unid.]=$C26)*(tblCompras[Data]=_xlfn.MAXIFS(tblCompras[Data],tblCompras[Produto],$B26,tblCompras[Unid.],$C26))),tblCompras[Preço Unit.]),"") -> 1.29 | N26: =IFERROR(LOOKUP(2,1/((tblCompras[Produto]=$B26)*(tblCompras[Unid.]=$C26)*(tblCompras[Data]=_xlfn.MAXIFS(tblCompras[Data],tblCompras[Produto],$B26,tblCompras[Unid.],$C26))),tblCompras[Mercado])&" · "&TEXT(DAY(_xlfn.MAXIFS(tblCompras[Data],tblCompras[Produto],$B26,tblCompras[Unid.],$C26)),"00")&"/"&TEXT(MONTH(_xlfn.MAXIFS(tblCompras[Data],tblCompras[Produto],$B26,tblCompras[Unid.],$C26)),"00")&"/"&TEXT(MOD(YEAR(_xlfn.MAXIFS(tblCompras[Data],tblCompras[Produto],$B26,tblCompras[Unid.],$C26)),100),"00"),"") -> Supermercados Nori · 09/08/26 | P26: =IF(AND(ISNUMBER($K26),$K26>0,OR($B$6="Todas",$D26=$B$6)),$K26+ROW()/100000,"") -> 0.36026
B27: AGUA MINERAL LEVE 490ML C/GAS | C27: FC | D27: Bebidas | E27: =IFERROR(_xlfn.MINIFS(tblCompras[Preço Unit.],tblCompras[Produto],$B27,tblCompras[Unid.],$C27),"") -> 2.5 | F27: =IFERROR(LOOKUP(2,1/((tblCompras[Produto]=$B27)*(tblCompras[Unid.]=$C27)*(tblCompras[Preço Unit.]=$E27)),tblCompras[Mercado]),"") -> Real Atacamix | G27: =IFERROR(LOOKUP(2,1/((tblCompras[Produto]=$B27)*(tblCompras[Unid.]=$C27)*(tblCompras[Preço Unit.]=$E27)),tblCompras[Data]),"") -> 46152 | H27: =IFERROR(_xlfn.MAXIFS(tblCompras[Preço Unit.],tblCompras[Produto],$B27,tblCompras[Unid.],$C27),"") -> 2.5 | I27: =IFERROR(LOOKUP(2,1/((tblCompras[Produto]=$B27)*(tblCompras[Unid.]=$C27)*(tblCompras[Preço Unit.]=$H27)),tblCompras[Mercado]),"") -> Real Atacamix | J27: =IFERROR(LOOKUP(2,1/((tblCompras[Produto]=$B27)*(tblCompras[Unid.]=$C27)*(tblCompras[Preço Unit.]=$H27)),tblCompras[Data]),"") -> 46152 | K27: =IF(OR($E27="",$H27=""),"",MAX(0,$H27-$E27)) -> 0 | L27: =IF(OR($E27="",$H27="",$E27=0),"",($H27-$E27)/$E27) -> 0 | M27: =IFERROR(LOOKUP(2,1/((tblCompras[Produto]=$B27)*(tblCompras[Unid.]=$C27)*(tblCompras[Data]=_xlfn.MAXIFS(tblCompras[Data],tblCompras[Produto],$B27,tblCompras[Unid.],$C27))),tblCompras[Preço Unit.]),"") -> 2.5 | N27: =IFERROR(LOOKUP(2,1/((tblCompras[Produto]=$B27)*(tblCompras[Unid.]=$C27)*(tblCompras[Data]=_xlfn.MAXIFS(tblCompras[Data],tblCompras[Produto],$B27,tblCompras[Unid.],$C27))),tblCompras[Mercado])&" · "&TEXT(DAY(_xlfn.MAXIFS(tblCompras[Data],tblCompras[Produto],$B27,tblCompras[Unid.],$C27)),"00")&"/"&TEXT(MONTH(_xlfn.MAXIFS(tblCompras[Data],tblCompras[Produto],$B27,tblCompras[Unid.],$C27)),"00")&"/"&TEXT(MOD(YEAR(_xlfn.MAXIFS(tblCompras[Data],tblCompras[Produto],$B27,tblCompras[Unid.],$C27)),100),"00"),"") -> Real Atacamix · 10/05/26 | P27: =IF(AND(ISNUMBER($K27),$K27>0,OR($B$6="Todas",$D27=$B$6)),$K27+ROW()/100000,"")
B28: Gatorade 350ml | C28: UN | D28: Bebidas | E28: =IFERROR(_xlfn.MINIFS(tblCompras[Preço Unit.],tblCompras[Produto],$B28,tblCompras[Unid.],$C28),"") -> 4.99 | F28: =IFERROR(LOOKUP(2,1/((tblCompras[Produto]=$B28)*(tblCompras[Unid.]=$C28)*(tblCompras[Preço Unit.]=$E28)),tblCompras[Mercado]),"") -> Supermercado Canesin | G28: =IFERROR(LOOKUP(2,1/((tblCompras[Produto]=$B28)*(tblCompras[Unid.]=$C28)*(tblCompras[Preço Unit.]=$E28)),tblCompras[Data]),"") -> 46161 | H28: =IFERROR(_xlfn.MAXIFS(tblCompras[Preço Unit.],tblCompras[Produto],$B28,tblCompras[Unid.],$C28),"") -> 4.99 | I28: =IFERROR(LOOKUP(2,1/((tblCompras[Produto]=$B28)*(tblCompras[Unid.]=$C28)*(tblCompras[Preço Unit.]=$H28)),tblCompras[Mercado]),"") -> Supermercado Canesin | J28: =IFERROR(LOOKUP(2,1/((tblCompras[Produto]=$B28)*(tblCompras[Unid.]=$C28)*(tblCompras[Preço Unit.]=$H28)),tblCompras[Data]),"") -> 46161 | K28: =IF(OR($E28="",$H28=""),"",MAX(0,$H28-$E28)) -> 0 | L28: =IF(OR($E28="",$H28="",$E28=0),"",($H28-$E28)/$E28) -> 0 | M28: =IFERROR(LOOKUP(2,1/((tblCompras[Produto]=$B28)*(tblCompras[Unid.]=$C28)*(tblCompras[Data]=_xlfn.MAXIFS(tblCompras[Data],tblCompras[Produto],$B28,tblCompras[Unid.],$C28))),tblCompras[Preço Unit.]),"") -> 4.99 | N28: =IFERROR(LOOKUP(2,1/((tblCompras[Produto]=$B28)*(tblCompras[Unid.]=$C28)*(tblCompras[Data]=_xlfn.MAXIFS(tblCompras[Data],tblCompras[Produto],$B28,tblCompras[Unid.],$C28))),tblCompras[Mercado])&" · "&TEXT(DAY(_xlfn.MAXIFS(tblCompras[Data],tblCompras[Produto],$B28,tblCompras[Unid.],$C28)),"00")&"/"&TEXT(MONTH(_xlfn.MAXIFS(tblCompras[Data],tblCompras[Produto],$B28,tblCompras[Unid.],$C28)),"00")&"/"&TEXT(MOD(YEAR(_xlfn.MAXIFS(tblCompras[Data],tblCompras[Produto],$B28,tblCompras[Unid.],$C28)),100),"00"),"") -> Supermercado Canesin · 19/05/26 | P28: =IF(AND(ISNUMBER($K28),$K28>0,OR($B$6="Todas",$D28=$B$6)),$K28+ROW()/100000,"")
B29: Gatorade Tangerina 500ml | C29: UN | D29: Bebidas | E29: =IFERROR(_xlfn.MINIFS(tblCompras[Preço Unit.],tblCompras[Produto],$B29,tblCompras[Unid.],$C29),"") -> 6.99 | F29: =IFERROR(LOOKUP(2,1/((tblCompras[Produto]=$B29)*(tblCompras[Unid.]=$C29)*(tblCompras[Preço Unit.]=$E29)),tblCompras[Mercado]),"") -> Canesin | G29: =IFERROR(LOOKUP(2,1/((tblCompras[Produto]=$B29)*(tblCompras[Unid.]=$C29)*(tblCompras[Preço Unit.]=$E29)),tblCompras[Data]),"") -> 46169 | H29: =IFERROR(_xlfn.MAXIFS(tblCompras[Preço Unit.],tblCompras[Produto],$B29,tblCompras[Unid.],$C29),"") -> 6.99 | I29: =IFERROR(LOOKUP(2,1/((tblCompras[Produto]=$B29)*(tblCompras[Unid.]=$C29)*(tblCompras[Preço Unit.]=$H29)),tblCompras[Mercado]),"") -> Canesin | J29: =IFERROR(LOOKUP(2,1/((tblCompras[Produto]=$B29)*(tblCompras[Unid.]=$C29)*(tblCompras[Preço Unit.]=$H29)),tblCompras[Data]),"") -> 46169 | K29: =IF(OR($E29="",$H29=""),"",MAX(0,$H29-$E29)) -> 0 | L29: =IF(OR($E29="",$H29="",$E29=0),"",($H29-$E29)/$E29) -> 0 | M29: =IFERROR(LOOKUP(2,1/((tblCompras[Produto]=$B29)*(tblCompras[Unid.]=$C29)*(tblCompras[Data]=_xlfn.MAXIFS(tblCompras[Data],tblCompras[Produto],$B29,tblCompras[Unid.],$C29))),tblCompras[Preço Unit.]),"") -> 6.99 | N29: =IFERROR(LOOKUP(2,1/((tblCompras[Produto]=$B29)*(tblCompras[Unid.]=$C29)*(tblCompras[Data]=_xlfn.MAXIFS(tblCompras[Data],tblCompras[Produto],$B29,tblCompras[Unid.],$C29))),tblCompras[Mercado])&" · "&TEXT(DAY(_xlfn.MAXIFS(tblCompras[Data],tblCompras[Produto],$B29,tblCompras[Unid.],$C29)),"00")&"/"&TEXT(MONTH(_xlfn.MAXIFS(tblCompras[Data],tblCompras[Produto],$B29,tblCompras[Unid.],$C29)),"00")&"/"&TEXT(MOD(YEAR(_xlfn.MAXIFS(tblCompras[Data],tblCompras[Produto],$B29,tblCompras[Unid.],$C29)),100),"00"),"") -> Canesin · 27/05/26 | P29: =IF(AND(ISNUMBER($K29),$K29>0,OR($B$6="Todas",$D29=$B$6)),$K29+ROW()/100000,"")
B30: Gatorade Uva 500ml | C30: UN | D30: Bebidas | E30: =IFERROR(_xlfn.MINIFS(tblCompras[Preço Unit.],tblCompras[Produto],$B30,tblCompras[Unid.],$C30),"") -> 6.99 | F30: =IFERROR(LOOKUP(2,1/((tblCompras[Produto]=$B30)*(tblCompras[Unid.]=$C30)*(tblCompras[Preço Unit.]=$E30)),tblCompras[Mercado]),"") -> Canesin | G30: =IFERROR(LOOKUP(2,1/((tblCompras[Produto]=$B30)*(tblCompras[Unid.]=$C30)*(tblCompras[Preço Unit.]=$E30)),tblCompras[Data]),"") -> 46168 | H30: =IFERROR(_xlfn.MAXIFS(tblCompras[Preço Unit.],tblCompras[Produto],$B30,tblCompras[Unid.],$C30),"") -> 6.99 | I30: =IFERROR(LOOKUP(2,1/((tblCompras[Produto]=$B30)*(tblCompras[Unid.]=$C30)*(tblCompras[Preço Unit.]=$H30)),tblCompras[Mercado]),"") -> Canesin | J30: =IFERROR(LOOKUP(2,1/((tblCompras[Produto]=$B30)*(tblCompras[Unid.]=$C30)*(tblCompras[Preço Unit.]=$H30)),tblCompras[Data]),"") -> 46168 | K30: =IF(OR($E30="",$H30=""),"",MAX(0,$H30-$E30)) -> 0 | L30: =IF(OR($E30="",$H30="",$E30=0),"",($H30-$E30)/$E30) -> 0 | M30: =IFERROR(LOOKUP(2,1/((tblCompras[Produto]=$B30)*(tblCompras[Unid.]=$C30)*(tblCompras[Data]=_xlfn.MAXIFS(tblCompras[Data],tblCompras[Produto],$B30,tblCompras[Unid.],$C30))),tblCompras[Preço Unit.]),"") -> 6.99 | N30: =IFERROR(LOOKUP(2,1/((tblCompras[Produto]=$B30)*(tblCompras[Unid.]=$C30)*(tblCompras[Data]=_xlfn.MAXIFS(tblCompras[Data],tblCompras[Produto],$B30,tblCompras[Unid.],$C30))),tblCompras[Mercado])&" · "&TEXT(DAY(_xlfn.MAXIFS(tblCompras[Data],tblCompras[Produto],$B30,tblCompras[Unid.],$C30)),"00")&"/"&TEXT(MONTH(_xlfn.MAXIFS(tblCompras[Data],tblCompras[Produto],$B30,tblCompras[Unid.],$C30)),"00")&"/"&TEXT(MOD(YEAR(_xlfn.MAXIFS(tblCompras[Data],tblCompras[Produto],$B30,tblCompras[Unid.],$C30)),100),"00"),"") -> Canesin · 26/05/26 | P30: =IF(AND(ISNUMBER($K30),$K30>0,OR($B$6="Todas",$D30=$B$6)),$K30+ROW()/100000,"")
B31: PEPSI 2L PET | C31: UN | D31: Bebidas | E31: =IFERROR(_xlfn.MINIFS(tblCompras[Preço Unit.],tblCompras[Produto],$B31,tblCompras[Unid.],$C31),"") -> 10.2 | F31: =IFERROR(LOOKUP(2,1/((tblCompras[Produto]=$B31)*(tblCompras[Unid.]=$C31)*(tblCompras[Preço Unit.]=$E31)),tblCompras[Mercado]),"") -> Andre Supermercado | G31: =IFERROR(LOOKUP(2,1/((tblCompras[Produto]=$B31)*(tblCompras[Unid.]=$C31)*(tblCompras[Preço Unit.]=$E31)),tblCompras[Data]),"") -> 46152 | H31: =IFERROR(_xlfn.MAXIFS(tblCompras[Preço Unit.],tblCompras[Produto],$B31,tblCompras[Unid.],$C31),"") -> 10.2 | I31: =IFERROR(LOOKUP(2,1/((tblCompras[Produto]=$B31)*(tblCompras[Unid.]=$C31)*(tblCompras[Preço Unit.]=$H31)),tblCompras[Mercado]),"") -> Andre Supermercado | J31: =IFERROR(LOOKUP(2,1/((tblCompras[Produto]=$B31)*(tblCompras[Unid.]=$C31)*(tblCompras[Preço Unit.]=$H31)),tblCompras[Data]),"") -> 46152 | K31: =IF(OR($E31="",$H31=""),"",MAX(0,$H31-$E31)) -> 0 | L31: =IF(OR($E31="",$H31="",$E31=0),"",($H31-$E31)/$E31) -> 0 | M31: =IFERROR(LOOKUP(2,1/((tblCompras[Produto]=$B31)*(tblCompras[Unid.]=$C31)*(tblCompras[Data]=_xlfn.MAXIFS(tblCompras[Data],tblCompras[Produto],$B31,tblCompras[Unid.],$C31))),tblCompras[Preço Unit.]),"") -> 10.2 | N31: =IFERROR(LOOKUP(2,1/((tblCompras[Produto]=$B31)*(tblCompras[Unid.]=$C31)*(tblCompras[Data]=_xlfn.MAXIFS(tblCompras[Data],tblCompras[Produto],$B31,tblCompras[Unid.],$C31))),tblCompras[Mercado])&" · "&TEXT(DAY(_xlfn.MAXIFS(tblCompras[Data],tblCompras[Produto],$B31,tblCompras[Unid.],$C31)),"00")&"/"&TEXT(MONTH(_xlfn.MAXIFS(tblCompras[Data],tblCompras[Produto],$B31,tblCompras[Unid.],$C31)),"00")&"/"&TEXT(MOD(YEAR(_xlfn.MAXIFS(tblCompras[Data],tblCompras[Produto],$B31,tblCompras[Unid.],$C31)),100),"00"),"") -> Andre Supermercado · 10/05/26 | P31: =IF(AND(ISNUMBER($K31),$K31>0,OR($B$6="Todas",$D31=$B$6)),$K31+ROW()/100000,"")
B32: Power Mix Frutas 500ml | C32: UN | D32: Bebidas | E32: =IFERROR(_xlfn.MINIFS(tblCompras[Preço Unit.],tblCompras[Produto],$B32,tblCompras[Unid.],$C32),"") -> 6.4 | F32: =IFERROR(LOOKUP(2,1/((tblCompras[Produto]=$B32)*(tblCompras[Unid.]=$C32)*(tblCompras[Preço Unit.]=$E32)),tblCompras[Mercado]),"") -> Andre Eduardo Hipolito | G32: =IFERROR(LOOKUP(2,1/((tblCompras[Produto]=$B32)*(tblCompras[Unid.]=$C32)*(tblCompras[Preço Unit.]=$E32)),tblCompras[Data]),"") -> 46162 | H32: =IFERROR(_xlfn.MAXIFS(tblCompras[Preço Unit.],tblCompras[Produto],$B32,tblCompras[Unid.],$C32),"") -> 6.4 | I32: =IFERROR(LOOKUP(2,1/((tblCompras[Produto]=$B32)*(tblCompras[Unid.]=$C32)*(tblCompras[Preço Unit.]=$H32)),tblCompras[Mercado]),"") -> Andre Eduardo Hipolito | J32: =IFERROR(LOOKUP(2,1/((tblCompras[Produto]=$B32)*(tblCompras[Unid.]=$C32)*(tblCompras[Preço Unit.]=$H32)),tblCompras[Data]),"") -> 46162 | K32: =IF(OR($E32="",$H32=""),"",MAX(0,$H32-$E32)) -> 0 | L32: =IF(OR($E32="",$H32="",$E32=0),"",($H32-$E32)/$E32) -> 0 | M32: =IFERROR(LOOKUP(2,1/((tblCompras[Produto]=$B32)*(tblCompras[Unid.]=$C32)*(tblCompras[Data]=_xlfn.MAXIFS(tblCompras[Data],tblCompras[Produto],$B32,tblCompras[Unid.],$C32))),tblCompras[Preço Unit.]),"") -> 6.4 | N32: =IFERROR(LOOKUP(2,1/((tblCompras[Produto]=$B32)*(tblCompras[Unid.]=$C32)*(tblCompras[Data]=_xlfn.MAXIFS(tblCompras[Data],tblCompras[Produto],$B32,tblCompras[Unid.],$C32))),tblCompras[Mercado])&" · "&TEXT(DAY(_xlfn.MAXIFS(tblCompras[Data],tblCompras[Produto],$B32,tblCompras[Unid.],$C32)),"00")&"/"&TEXT(MONTH(_xlfn.MAXIFS(tblCompras[Data],tblCompras[Produto],$B32,tblCompras[Unid.],$C32)),"00")&"/"&TEXT(MOD(YEAR(_xlfn.MAXIFS(tblCompras[Data],tblCompras[Produto],$B32,tblCompras[Unid.],$C32)),100),"00"),"") -> Andre Eduardo Hipolito · 20/05/26 | P32: =IF(AND(ISNUMBER($K32),$K32>0,OR($B$6="Todas",$D32=$B$6)),$K32+ROW()/100000,"")
B33: Suco de Uva Garibaldi | C33: UN | D33: Bebidas | E33: =IFERROR(_xlfn.MINIFS(tblCompras[Preço Unit.],tblCompras[Produto],$B33,tblCompras[Unid.],$C33),"") -> 16.4 | F33: =IFERROR(LOOKUP(2,1/((tblCompras[Produto]=$B33)*(tblCompras[Unid.]=$C33)*(tblCompras[Preço Unit.]=$E33)),tblCompras[Mercado]),"") -> Supermercados Nori | G33: =IFERROR(LOOKUP(2,1/((tblCompras[Produto]=$B33)*(tblCompras[Unid.]=$C33)*(tblCompras[Preço Unit.]=$E33)),tblCompras[Data]),"") -> 46157 | H33: =IFERROR(_xlfn.MAXIFS(tblCompras[Preço Unit.],tblCompras[Produto],$B33,tblCompras[Unid.],$C33),"") -> 16.4 | I33: =IFERROR(LOOKUP(2,1/((tblCompras[Produto]=$B33)*(tblCompras[Unid.]=$C33)*(tblCompras[Preço Unit.]=$H33)),tblCompras[Mercado]),"") -> Supermercados Nori | J33: =IFERROR(LOOKUP(2,1/((tblCompras[Produto]=$B33)*(tblCompras[Unid.]=$C33)*(tblCompras[Preço Unit.]=$H33)),tblCompras[Data]),"") -> 46157 | K33: =IF(OR($E33="",$H33=""),"",MAX(0,$H33-$E33)) -> 0 | L33: =IF(OR($E33="",$H33="",$E33=0),"",($H33-$E33)/$E33) -> 0 | M33: =IFERROR(LOOKUP(2,1/((tblCompras[Produto]=$B33)*(tblCompras[Unid.]=$C33)*(tblCompras[Data]=_xlfn.MAXIFS(tblCompras[Data],tblCompras[Produto],$B33,tblCompras[Unid.],$C33))),tblCompras[Preço Unit.]),"") -> 16.4 | N33: =IFERROR(LOOKUP(2,1/((tblCompras[Produto]=$B33)*(tblCompras[Unid.]=$C33)*(tblCompras[Data]=_xlfn.MAXIFS(tblCompras[Data],tblCompras[Produto],$B33,tblCompras[Unid.],$C33))),tblCompras[Mercado])&" · "&TEXT(DAY(_xlfn.MAXIFS(tblCompras[Data],tblCompras[Produto],$B33,tblCompras[Unid.],$C33)),"00")&"/"&TEXT(MONTH(_xlfn.MAXIFS(tblCompras[Data],tblCompras[Produto],$B33,tblCompras[Unid.],$C33)),"00")&"/"&TEXT(MOD(YEAR(_xlfn.MAXIFS(tblCompras[Data],tblCompras[Produto],$B33,tblCompras[Unid.],$C33)),100),"00"),"") -> Supermercados Nori · 15/05/26 | P33: =IF(AND(ISNUMBER($K33),$K33>0,OR($B$6="Todas",$D33=$B$6)),$K33+ROW()/100000,"")
B34: VINHO SANTA CAROLINA | C34: UN | D34: Bebidas | E34: =IFERROR(_xlfn.MINIFS(tblCompras[Preço Unit.],tblCompras[Produto],$B34,tblCompras[Unid.],$C34),"") -> 18.9 | F34: =IFERROR(LOOKUP(2,1/((tblCompras[Produto]=$B34)*(tblCompras[Unid.]=$C34)*(tblCompras[Preço Unit.]=$E34)),tblCompras[Mercado]),"") -> Supermercados Nori | G34: =IFERROR(LOOKUP(2,1/((tblCompras[Produto]=$B34)*(tblCompras[Unid.]=$C34)*(tblCompras[Preço Unit.]=$E34)),tblCompras[Data]),"") -> 46146 | H34: =IFERROR(_xlfn.MAXIFS(tblCompras[Preço Unit.],tblCompras[Produto],$B34,tblCompras[Unid.],$C34),"") -> 18.9 | I34: =IFERROR(LOOKUP(2,1/((tblCompras[Produto]=$B34)*(tblCompras[Unid.]=$C34)*(tblCompras[Preço Unit.]=$H34)),tblCompras[Mercado]),"") -> Supermercados Nori | J34: =IFERROR(LOOKUP(2,1/((tblCompras[Produto]=$B34)*(tblCompras[Unid.]=$C34)*(tblCompras[Preço Unit.]=$H34)),tblCompras[Data]),"") -> 46146 | K34: =IF(OR($E34="",$H34=""),"",MAX(0,$H34-$E34)) -> 0 | L34: =IF(OR($E34="",$H34="",$E34=0),"",($H34-$E34)/$E34) -> 0 | M34: =IFERROR(LOOKUP(2,1/((tblCompras[Produto]=$B34)*(tblCompras[Unid.]=$C34)*(tblCompras[Data]=_xlfn.MAXIFS(tblCompras[Data],tblCompras[Produto],$B34,tblCompras[Unid.],$C34))),tblCompras[Preço Unit.]),"") -> 18.9 | N34: =IFERROR(LOOKUP(2,1/((tblCompras[Produto]=$B34)*(tblCompras[Unid.]=$C34)*(tblCompras[Data]=_xlfn.MAXIFS(tblCompras[Data],tblCompras[Produto],$B34,tblCompras[Unid.],$C34))),tblCompras[Mercado])&" · "&TEXT(DAY(_xlfn.MAXIFS(tblCompras[Data],tblCompras[Produto],$B34,tblCompras[Unid.],$C34)),"00")&"/"&TEXT(MONTH(_xlfn.MAXIFS(tblCompras[Data],tblCompras[Produto],$B34,tblCompras[Unid.],$C34)),"00")&"/"&TEXT(MOD(YEAR(_xlfn.MAXIFS(tblCompras[Data],tblCompras[Produto],$B34,tblCompras[Unid.],$C34)),100),"00"),"") -> Supermercados Nori · 24/05/26 | P34: =IF(AND(ISNUMBER($K34),$K34>0,OR($B$6="Todas",$D34=$B$6)),$K34+ROW()/100000,"")
B35: Vinho Santa Carolina | C35: UN | D35: Bebidas | E35: =IFERROR(_xlfn.MINIFS(tblCompras[Preço Unit.],tblCompras[Produto],$B35,tblCompras[Unid.],$C35),"") -> 18.9 | F35: =IFERROR(LOOKUP(2,1/((tblCompras[Produto]=$B35)*(tblCompras[Unid.]=$C35)*(tblCompras[Preço Unit.]=$E35)),tblCompras[Mercado]),"") -> Supermercados Nori | G35: =IFERROR(LOOKUP(2,1/((tblCompras[Produto]=$B35)*(tblCompras[Unid.]=$C35)*(tblCompras[Preço Unit.]=$E35)),tblCompras[Data]),"") -> 46146 | H35: =IFERROR(_xlfn.MAXIFS(tblCompras[Preço Unit.],tblCompras[Produto],$B35,tblCompras[Unid.],$C35),"") -> 18.9 | I35: =IFERROR(LOOKUP(2,1/((tblCompras[Produto]=$B35)*(tblCompras[Unid.]=$C35)*(tblCompras[Preço Unit.]=$H35)),tblCompras[Mercado]),"") -> Supermercados Nori | J35: =IFERROR(LOOKUP(2,1/((tblCompras[Produto]=$B35)*(tblCompras[Unid.]=$C35)*(tblCompras[Preço Unit.]=$H35)),tblCompras[Data]),"") -> 46146 | K35: =IF(OR($E35="",$H35=""),"",MAX(0,$H35-$E35)) -> 0 | L35: =IF(OR($E35="",$H35="",$E35=0),"",($H35-$E35)/$E35) -> 0 | M35: =IFERROR(LOOKUP(2,1/((tblCompras[Produto]=$B35)*(tblCompras[Unid.]=$C35)*(tblCompras[Data]=_xlfn.MAXIFS(tblCompras[Data],tblCompras[Produto],$B35,tblCompras[Unid.],$C35))),tblCompras[Preço Unit.]),"") -> 18.9 | N35: =IFERROR(LOOKUP(2,1/((tblCompras[Produto]=$B35)*(tblCompras[Unid.]=$C35)*(tblCompras[Data]=_xlfn.MAXIFS(tblCompras[Data],tblCompras[Produto],$B35,tblCompras[Unid.],$C35))),tblCompras[Mercado])&" · "&TEXT(DAY(_xlfn.MAXIFS(tblCompras[Data],tblCompras[Produto],$B35,tblCompras[Unid.],$C35)),"00")&"/"&TEXT(MONTH(_xlfn.MAXIFS(tblCompras[Data],tblCompras[Produto],$B35,tblCompras[Unid.],$C35)),"00")&"/"&TEXT(MOD(YEAR(_xlfn.MAXIFS(tblCompras[Data],tblCompras[Produto],$B35,tblCompras[Unid.],$C35)),100),"00"),"") -> Supermercados Nori · 24/05/26 | P35: =IF(AND(ISNUMBER($K35),$K35>0,OR($B$6="Todas",$D35=$B$6)),$K35+ROW()/100000,"")
B36: Café La Sante | C36: UN | D36: Café | E36: =IFERROR(_xlfn.MINIFS(tblCompras[Preço Unit.],tblCompras[Produto],$B36,tblCompras[Unid.],$C36),"") -> 27 | F36: =IFERROR(LOOKUP(2,1/((tblCompras[Produto]=$B36)*(tblCompras[Unid.]=$C36)*(tblCompras[Preço Unit.]=$E36)),tblCompras[Mercado]),"") -> Supermercados Nori | G36: =IFERROR(LOOKUP(2,1/((tblCompras[Produto]=$B36)*(tblCompras[Unid.]=$C36)*(tblCompras[Preço Unit.]=$E36)),tblCompras[Data]),"") -> 46146 | H36: =IFERROR(_xlfn.MAXIFS(tblCompras[Preço Unit.],tblCompras[Produto],$B36,tblCompras[Unid.],$C36),"") -> 27 | I36: =IFERROR(LOOKUP(2,1/((tblCompras[Produto]=$B36)*(tblCompras[Unid.]=$C36)*(tblCompras[Preço Unit.]=$H36)),tblCompras[Mercado]),"") -> Supermercados Nori | J36: =IFERROR(LOOKUP(2,1/((tblCompras[Produto]=$B36)*(tblCompras[Unid.]=$C36)*(tblCompras[Preço Unit.]=$H36)),tblCompras[Data]),"") -> 46146 | K36: =IF(OR($E36="",$H36=""),"",MAX(0,$H36-$E36)) -> 0 | L36: =IF(OR($E36="",$H36="",$E36=0),"",($H36-$E36)/$E36) -> 0 | M36: =IFERROR(LOOKUP(2,1/((tblCompras[Produto]=$B36)*(tblCompras[Unid.]=$C36)*(tblCompras[Data]=_xlfn.MAXIFS(tblCompras[Data],tblCompras[Produto],$B36,tblCompras[Unid.],$C36))),tblCompras[Preço Unit.]),"") -> 27 | N36: =IFERROR(LOOKUP(2,1/((tblCompras[Produto]=$B36)*(tblCompras[Unid.]=$C36)*(tblCompras[Data]=_xlfn.MAXIFS(tblCompras[Data],tblCompras[Produto],$B36,tblCompras[Unid.],$C36))),tblCompras[Mercado])&" · "&TEXT(DAY(_xlfn.MAXIFS(tblCompras[Data],tblCompras[Produto],$B36,tblCompras[Unid.],$C36)),"00")&"/"&TEXT(MONTH(_xlfn.MAXIFS(tblCompras[Data],tblCompras[Produto],$B36,tblCompras[Unid.],$C36)),"00")&"/"&TEXT(MOD(YEAR(_xlfn.MAXIFS(tblCompras[Data],tblCompras[Produto],$B36,tblCompras[Unid.],$C36)),100),"00"),"") -> Supermercados Nori · 04/05/26 | P36: =IF(AND(ISNUMBER($K36),$K36>0,OR($B$6="Todas",$D36=$B$6)),$K36+ROW()/100000,"")
... B218: VALDA DIET 50GR | C218: UN | D218: Saúde | E218: =IFERROR(_xlfn.MINIFS(tblCompras[Preço Unit.],tblCompras[Produto],$B218,tblCompras[Unid.],$C218),"") -> 34.56 | F218: =IFERROR(LOOKUP(2,1/((tblCompras[Produto]=$B218)*(tblCompras[Unid.]=$C218)*(tblCompras[Preço Unit.]=$E218)),tblCompras[Mercado]),"") -> Lanchoti e Martins | G218: =IFERROR(LOOKUP(2,1/((tblCompras[Produto]=$B218)*(tblCompras[Unid.]=$C218)*(tblCompras[Preço Unit.]=$E218)),tblCompras[Data]),"") -> 46183 | H218: =IFERROR(_xlfn.MAXIFS(tblCompras[Preço Unit.],tblCompras[Produto],$B218,tblCompras[Unid.],$C218),"") -> 34.56 | I218: =IFERROR(LOOKUP(2,1/((tblCompras[Produto]=$B218)*(tblCompras[Unid.]=$C218)*(tblCompras[Preço Unit.]=$H218)),tblCompras[Mercado]),"") -> Lanchoti e Martins | J218: =IFERROR(LOOKUP(2,1/((tblCompras[Produto]=$B218)*(tblCompras[Unid.]=$C218)*(tblCompras[Preço Unit.]=$H218)),tblCompras[Data]),"") -> 46183 | K218: =IF(OR($E218="",$H218=""),"",MAX(0,$H218-$E218)) -> 0 | L218: =IF(OR($E218="",$H218="",$E218=0),"",($H218-$E218)/$E218) -> 0 | M218: =IFERROR(LOOKUP(2,1/((tblCompras[Produto]=$B218)*(tblCompras[Unid.]=$C218)*(tblCompras[Data]=_xlfn.MAXIFS(tblCompras[Data],tblCompras[Produto],$B218,tblCompras[Unid.],$C218))),tblCompras[Preço Unit.]),"") -> 34.56 | N218: =IFERROR(LOOKUP(2,1/((tblCompras[Produto]=$B218)*(tblCompras[Unid.]=$C218)*(tblCompras[Data]=_xlfn.MAXIFS(tblCompras[Data],tblCompras[Produto],$B218,tblCompras[Unid.],$C218))),tblCompras[Mercado])&" · "&TEXT(DAY(_xlfn.MAXIFS(tblCompras[Data],tblCompras[Produto],$B218,tblCompras[Unid.],$C218)),"00")&"/"&TEXT(MONTH(_xlfn.MAXIFS(tblCompras[Data],tblCompras[Produto],$B218,tblCompras[Unid.],$C218)),"00")&"/"&TEXT(MOD(YEAR(_xlfn.MAXIFS(tblCompras[Data],tblCompras[Produto],$B218,tblCompras[Unid.],$C218)),100),"00"),"") -> Lanchoti e Martins · 10/06/26 | P218: =IF(AND(ISNUMBER($K218),$K218>0,OR($B$6="Todas",$D218=$B$6)),$K218+ROW()/100000,"")
B220: Cálculos automáticos a partir da aba Compras (tblCompras). Para acompanhar um produto novo, inclua nome, unidade e categoria numa linha desta lista.

Sheet Listas
A1: Listas
A2: Categorias e unidades padrao.
A4: Categorias | B4: Unidades | C4: Mercados | E4: Meses (filtro) | F4: Categorias (filtro) | G4: Mercados (filtro) | H4: Início do mês (aux)
A5: Mercearia | B5: UN | C5: Supermercados Nori | E5: (Todos) | F5: (Todos) | G5: (Todos)
A6: Laticinios | B6: KG | C6: Mercado A | E6: =IF(EDATE(MIN(tblCompras[Data]),0)>EOMONTH(MAX(tblCompras[Data]),0),"",CHOOSE(MONTH(EDATE(MIN(tblCompras[Data]),0)),"jan","fev","mar","abr","mai","jun","jul","ago","set","out","nov","dez")&"/"&YEAR(EDATE(MIN(tblCompras[Data]),0))) -> mai/2026 | F6: Mercearia | G6: Supermercados Nori | H6: =IF(E6="","",EOMONTH(MIN(tblCompras[Data]),0-1)+1) -> 46143
A7: Limpeza | B7: LT | C7: Mercado B | E7: =IF(EDATE(MIN(tblCompras[Data]),1)>EOMONTH(MAX(tblCompras[Data]),0),"",CHOOSE(MONTH(EDATE(MIN(tblCompras[Data]),1)),"jan","fev","mar","abr","mai","jun","jul","ago","set","out","nov","dez")&"/"&YEAR(EDATE(MIN(tblCompras[Data]),1))) -> jun/2026 | F7: Laticinios | G7: Supermercado Canesin | H7: =IF(E7="","",EOMONTH(MIN(tblCompras[Data]),1-1)+1) -> 46174
A8: Padaria | B8: ML | C8: Mercado C | E8: =IF(EDATE(MIN(tblCompras[Data]),2)>EOMONTH(MAX(tblCompras[Data]),0),"",CHOOSE(MONTH(EDATE(MIN(tblCompras[Data]),2)),"jan","fev","mar","abr","mai","jun","jul","ago","set","out","nov","dez")&"/"&YEAR(EDATE(MIN(tblCompras[Data]),2))) -> jul/2026 | F8: Padaria | G8: Varejao Monteverde | H8: =IF(E8="","",EOMONTH(MIN(tblCompras[Data]),2-1)+1) -> 46204
A9: Pet | B9: G | C9: Nubank | E9: =IF(EDATE(MIN(tblCompras[Data]),3)>EOMONTH(MAX(tblCompras[Data]),0),"",CHOOSE(MONTH(EDATE(MIN(tblCompras[Data]),3)),"jan","fev","mar","abr","mai","jun","jul","ago","set","out","nov","dez")&"/"&YEAR(EDATE(MIN(tblCompras[Data]),3))) -> ago/2026 | F9: Hortifruti | G9: Andre Eduardo Hipolito | H9: =IF(E9="","",EOMONTH(MIN(tblCompras[Data]),3-1)+1) -> 46235
A10: Hortifruti | B10: PACOTE | C10: Varejao Monteverde | E10: =IF(EDATE(MIN(tblCompras[Data]),4)>EOMONTH(MAX(tblCompras[Data]),0),"",CHOOSE(MONTH(EDATE(MIN(tblCompras[Data]),4)),"jan","fev","mar","abr","mai","jun","jul","ago","set","out","nov","dez")&"/"&YEAR(EDATE(MIN(tblCompras[Data]),4))) | F10: Bebidas | G10: Varejao Nova Brasil | H10: =IF(E10="","",EOMONTH(MIN(tblCompras[Data]),4-1)+1)
A11: Carnes | B11: Crystal | C11: Varejao Nova Brasil | E11: =IF(EDATE(MIN(tblCompras[Data]),5)>EOMONTH(MAX(tblCompras[Data]),0),"",CHOOSE(MONTH(EDATE(MIN(tblCompras[Data]),5)),"jan","fev","mar","abr","mai","jun","jul","ago","set","out","nov","dez")&"/"&YEAR(EDATE(MIN(tblCompras[Data]),5))) | F11: Carnes | G11: Casa de Carnes Barao da Carne | H11: =IF(E11="","",EOMONTH(MIN(tblCompras[Data]),5-1)+1)
A12: Bebidas | C12: Andre Novato Ribeiro | E12: =IF(EDATE(MIN(tblCompras[Data]),6)>EOMONTH(MAX(tblCompras[Data]),0),"",CHOOSE(MONTH(EDATE(MIN(tblCompras[Data]),6)),"jan","fev","mar","abr","mai","jun","jul","ago","set","out","nov","dez")&"/"&YEAR(EDATE(MIN(tblCompras[Data]),6))) | F12: Higiene | G12: Lanchoti e Martins | H12: =IF(E12="","",EOMONTH(MIN(tblCompras[Data]),6-1)+1)
A13: Higiene | C13: Supermercado Canesin | E13: =IF(EDATE(MIN(tblCompras[Data]),7)>EOMONTH(MAX(tblCompras[Data]),0),"",CHOOSE(MONTH(EDATE(MIN(tblCompras[Data]),7)),"jan","fev","mar","abr","mai","jun","jul","ago","set","out","nov","dez")&"/"&YEAR(EDATE(MIN(tblCompras[Data]),7))) | F13: Limpeza | G13: Andre Novato Ribeiro | H13: =IF(E13="","",EOMONTH(MIN(tblCompras[Data]),7-1)+1)
A14: Cartao/Fatura | C14: Lanchoti e Martins | E14: =IF(EDATE(MIN(tblCompras[Data]),8)>EOMONTH(MAX(tblCompras[Data]),0),"",CHOOSE(MONTH(EDATE(MIN(tblCompras[Data]),8)),"jan","fev","mar","abr","mai","jun","jul","ago","set","out","nov","dez")&"/"&YEAR(EDATE(MIN(tblCompras[Data]),8))) | F14: Laticínios | G14: Real Atacamix | H14: =IF(E14="","",EOMONTH(MIN(tblCompras[Data]),8-1)+1)
A15: Saúde | C15: Andre Eduardo Hipolito | E15: =IF(EDATE(MIN(tblCompras[Data]),9)>EOMONTH(MAX(tblCompras[Data]),0),"",CHOOSE(MONTH(EDATE(MIN(tblCompras[Data]),9)),"jan","fev","mar","abr","mai","jun","jul","ago","set","out","nov","dez")&"/"&YEAR(EDATE(MIN(tblCompras[Data]),9))) | F15: Saúde | G15: Crystal | H15: =IF(E15="","",EOMONTH(MIN(tblCompras[Data]),9-1)+1)
E16: =IF(EDATE(MIN(tblCompras[Data]),10)>EOMONTH(MAX(tblCompras[Data]),0),"",CHOOSE(MONTH(EDATE(MIN(tblCompras[Data]),10)),"jan","fev","mar","abr","mai","jun","jul","ago","set","out","nov","dez")&"/"&YEAR(EDATE(MIN(tblCompras[Data]),10))) | F16: Pet | G16: André | H16: =IF(E16="","",EOMONTH(MIN(tblCompras[Data]),10-1)+1)
E17: =IF(EDATE(MIN(tblCompras[Data]),11)>EOMONTH(MAX(tblCompras[Data]),0),"",CHOOSE(MONTH(EDATE(MIN(tblCompras[Data]),11)),"jan","fev","mar","abr","mai","jun","jul","ago","set","out","nov","dez")&"/"&YEAR(EDATE(MIN(tblCompras[Data]),11))) | F17: Café | G17: Andre Supermercado | H17: =IF(E17="","",EOMONTH(MIN(tblCompras[Data]),11-1)+1)
F18: Rotisseria | G18: Canesin
E19: Nota: os meses são gerados por fórmula a partir da tabela Compras (até 12 meses). Se surgir uma categoria ou mercado novo na aba Compras, adicione-o também nas colunas F/G para que apareça nos filtros e no Painel. | F19: Frios
F20: Açougue
F21: Frutas
